[{"station":"KCAMALIB62","date":"2022-01-31 00:04:00","temperature":53.1,"wind_speed":1.3,"wind_gust":2.2,"dew_point":41.2,"wind_chill":53.1,"heat_index":53.1,"pressure":30.04,"precip_rate":0,"precip_total":0,"humidity":64,"wind_dir":328},{"station":"KCAMALIB62","date":"2022-01-31 00:09:00","temperature":52.9,"wind_speed":0.2,"wind_gust":1.1,"dew_point":41.2,"wind_chill":52.9,"heat_index":52.9,"pressure":30.04,"precip_rate":0,"precip_total":0,"humidity":67,"wind_dir":312},{"station":"KCAMALIB62","date":"2022-01-31 00:14:00","temperature":51.6,"wind_speed":0,"wind_gust":0,"dew_point":41.1,"wind_chill":51.6,"heat_index":51.6,"pressure":30.04,"precip_rate":0,"precip_total":0,"humidity":69,"wind_dir":309},{"station":"KCAMALIB62","date":"2022-01-31 00:19:00","temperature":50.7,"wind_speed":0,"wind_gust":0,"dew_point":41,"wind_chill":50.7,"heat_index":50.7,"pressure":30.03,"precip_rate":0,"precip_total":0,"humidity":70,"wind_dir":307},{"station":"KCAMALIB62","date":"2022-01-31 00:24:00","temperature":50,"wind_speed":0,"wind_gust":0,"dew_point":40.6,"wind_chill":50,"heat_index":50,"pressure":30.03,"precip_rate":0,"precip_total":0,"humidity":70,"wind_dir":315},{"station":"KCAMALIB62","date":"2022-01-31 00:29:00","temperature":50,"wind_speed":0,"wind_gust":0,"dew_point":40.6,"wind_chill":50,"heat_index":50,"pressure":30.04,"precip_rate":0,"precip_total":0,"humidity":70,"wind_dir":312},{"station":"KCAMALIB62","date":"2022-01-31 00:34:00","temperature":50,"wind_speed":0.2,"wind_gust":1.1,"dew_point":40.6,"wind_chill":50,"heat_index":50,"pressure":30.03,"precip_rate":0,"precip_total":0,"humidity":70,"wind_dir":327},{"station":"KCAMALIB62","date":"2022-01-31 00:39:00","temperature":50,"wind_speed":0,"wind_gust":0,"dew_point":40.8,"wind_chill":50,"heat_index":50,"pressure":30.03,"precip_rate":0,"precip_total":0,"humidity":71,"wind_dir":314},{"station":"KCAMALIB62","date":"2022-01-31 00:44:00","temperature":49.6,"wind_speed":0,"wind_gust":0,"dew_point":40.6,"wind_chill":49.6,"heat_index":49.6,"pressure":30.03,"precip_rate":0,"precip_total":0,"humidity":71,"wind_dir":303},{"station":"KCAMALIB62","date":"2022-01-31 00:49:00","temperature":49.8,"wind_speed":0,"wind_gust":0,"dew_point":39.9,"wind_chill":49.8,"heat_index":49.8,"pressure":30.03,"precip_rate":0,"precip_total":0,"humidity":69,"wind_dir":307},{"station":"KCAMALIB62","date":"2022-01-31 00:54:00","temperature":49.8,"wind_speed":0.9,"wind_gust":1.1,"dew_point":40.7,"wind_chill":49.8,"heat_index":49.8,"pressure":30.03,"precip_rate":0,"precip_total":0,"humidity":72,"wind_dir":307},{"station":"KCAMALIB62","date":"2022-01-31 00:59:00","temperature":49.3,"wind_speed":0,"wind_gust":0,"dew_point":40.7,"wind_chill":49.3,"heat_index":49.3,"pressure":30.03,"precip_rate":0,"precip_total":0,"humidity":72,"wind_dir":311},{"station":"KCAMALIB62","date":"2022-01-31 01:04:00","temperature":48.7,"wind_speed":0,"wind_gust":0,"dew_point":40.1,"wind_chill":48.7,"heat_index":48.7,"pressure":30.03,"precip_rate":0,"precip_total":0,"humidity":72,"wind_dir":308},{"station":"KCAMALIB62","date":"2022-01-31 01:09:00","temperature":48.6,"wind_speed":0.2,"wind_gust":1.1,"dew_point":38.3,"wind_chill":48.6,"heat_index":48.6,"pressure":30.03,"precip_rate":0,"precip_total":0,"humidity":68,"wind_dir":312},{"station":"KCAMALIB62","date":"2022-01-31 01:14:00","temperature":48.4,"wind_speed":0,"wind_gust":0,"dew_point":38.5,"wind_chill":48.4,"heat_index":48.4,"pressure":30.02,"precip_rate":0,"precip_total":0,"humidity":69,"wind_dir":317},{"station":"KCAMALIB62","date":"2022-01-31 01:19:00","temperature":48,"wind_speed":0,"wind_gust":0,"dew_point":38.7,"wind_chill":48,"heat_index":48,"pressure":30.02,"precip_rate":0,"precip_total":0,"humidity":70,"wind_dir":312},{"station":"KCAMALIB62","date":"2022-01-31 01:24:00","temperature":47.8,"wind_speed":0,"wind_gust":0,"dew_point":38.5,"wind_chill":47.8,"heat_index":47.8,"pressure":30.02,"precip_rate":0,"precip_total":0,"humidity":70,"wind_dir":311},{"station":"KCAMALIB62","date":"2022-01-31 01:29:00","temperature":47.7,"wind_speed":0,"wind_gust":0,"dew_point":38,"wind_chill":47.7,"heat_index":47.7,"pressure":30.02,"precip_rate":0,"precip_total":0,"humidity":69,"wind_dir":314},{"station":"KCAMALIB62","date":"2022-01-31 01:34:00","temperature":47.5,"wind_speed":0,"wind_gust":0,"dew_point":37.8,"wind_chill":47.5,"heat_index":47.5,"pressure":30.02,"precip_rate":0,"precip_total":0,"humidity":69,"wind_dir":304},{"station":"KCAMALIB62","date":"2022-01-31 01:39:00","temperature":47.5,"wind_speed":0,"wind_gust":0,"dew_point":37.1,"wind_chill":47.5,"heat_index":47.5,"pressure":30.02,"precip_rate":0,"precip_total":0,"humidity":67,"wind_dir":307},{"station":"KCAMALIB62","date":"2022-01-31 01:44:00","temperature":47.5,"wind_speed":0.9,"wind_gust":1.1,"dew_point":36.7,"wind_chill":47.5,"heat_index":47.5,"pressure":30.02,"precip_rate":0,"precip_total":0,"humidity":66,"wind_dir":320},{"station":"KCAMALIB62","date":"2022-01-31 01:49:00","temperature":47.5,"wind_speed":0.2,"wind_gust":1.1,"dew_point":36.5,"wind_chill":47.5,"heat_index":47.5,"pressure":30.02,"precip_rate":0,"precip_total":0,"humidity":66,"wind_dir":328},{"station":"KCAMALIB62","date":"2022-01-31 01:54:00","temperature":47.8,"wind_speed":0.4,"wind_gust":1.1,"dew_point":36.1,"wind_chill":47.8,"heat_index":47.8,"pressure":30.02,"precip_rate":0,"precip_total":0,"humidity":64,"wind_dir":314},{"station":"KCAMALIB62","date":"2022-01-31 01:59:00","temperature":48,"wind_speed":0,"wind_gust":0,"dew_point":36.4,"wind_chill":48,"heat_index":48,"pressure":30.01,"precip_rate":0,"precip_total":0,"humidity":64,"wind_dir":314},{"station":"KCAMALIB62","date":"2022-01-31 02:04:00","temperature":48.2,"wind_speed":0.4,"wind_gust":1.1,"dew_point":36.4,"wind_chill":48.2,"heat_index":48.2,"pressure":30.01,"precip_rate":0,"precip_total":0,"humidity":64,"wind_dir":312},{"station":"KCAMALIB62","date":"2022-01-31 02:09:00","temperature":48.6,"wind_speed":0.2,"wind_gust":1.1,"dew_point":36.6,"wind_chill":48.6,"heat_index":48.6,"pressure":30.01,"precip_rate":0,"precip_total":0,"humidity":63,"wind_dir":321},{"station":"KCAMALIB62","date":"2022-01-31 02:14:00","temperature":48.9,"wind_speed":0.9,"wind_gust":1.1,"dew_point":36,"wind_chill":48.9,"heat_index":48.9,"pressure":30.01,"precip_rate":0,"precip_total":0,"humidity":61,"wind_dir":321},{"station":"KCAMALIB62","date":"2022-01-31 02:19:00","temperature":48.7,"wind_speed":0.4,"wind_gust":1.1,"dew_point":35.9,"wind_chill":48.7,"heat_index":48.7,"pressure":30.01,"precip_rate":0,"precip_total":0,"humidity":61,"wind_dir":310},{"station":"KCAMALIB62","date":"2022-01-31 02:24:00","temperature":48.4,"wind_speed":0.9,"wind_gust":1.1,"dew_point":35.6,"wind_chill":48.4,"heat_index":48.4,"pressure":30.01,"precip_rate":0,"precip_total":0,"humidity":61,"wind_dir":320},{"station":"KCAMALIB62","date":"2022-01-31 02:29:00","temperature":48.4,"wind_speed":1.1,"wind_gust":1.1,"dew_point":35,"wind_chill":48.4,"heat_index":48.4,"pressure":30.01,"precip_rate":0,"precip_total":0,"humidity":60,"wind_dir":319},{"station":"KCAMALIB62","date":"2022-01-31 02:34:00","temperature":48.9,"wind_speed":0.9,"wind_gust":1.1,"dew_point":35.9,"wind_chill":48.9,"heat_index":48.9,"pressure":30.01,"precip_rate":0,"precip_total":0,"humidity":61,"wind_dir":314},{"station":"KCAMALIB62","date":"2022-01-31 02:39:00","temperature":48.4,"wind_speed":0,"wind_gust":0,"dew_point":35.8,"wind_chill":48.4,"heat_index":48.4,"pressure":30,"precip_rate":0,"precip_total":0,"humidity":62,"wind_dir":324},{"station":"KCAMALIB62","date":"2022-01-31 02:44:00","temperature":47.8,"wind_speed":0.2,"wind_gust":1.1,"dew_point":35,"wind_chill":47.8,"heat_index":47.8,"pressure":30.01,"precip_rate":0,"precip_total":0,"humidity":61,"wind_dir":307},{"station":"KCAMALIB62","date":"2022-01-31 02:49:00","temperature":47.7,"wind_speed":0.7,"wind_gust":1.1,"dew_point":34.9,"wind_chill":47.7,"heat_index":47.7,"pressure":30.01,"precip_rate":0,"precip_total":0,"humidity":61,"wind_dir":305},{"station":"KCAMALIB62","date":"2022-01-31 02:54:00","temperature":47.7,"wind_speed":1.8,"wind_gust":2.2,"dew_point":34.9,"wind_chill":47.7,"heat_index":47.7,"pressure":30.01,"precip_rate":0,"precip_total":0,"humidity":61,"wind_dir":324},{"station":"KCAMALIB62","date":"2022-01-31 02:59:00","temperature":48.4,"wind_speed":0.2,"wind_gust":1.1,"dew_point":35.2,"wind_chill":48.4,"heat_index":48.4,"pressure":30,"precip_rate":0,"precip_total":0,"humidity":60,"wind_dir":307},{"station":"KCAMALIB62","date":"2022-01-31 03:04:00","temperature":48.6,"wind_speed":0.2,"wind_gust":1.1,"dew_point":36,"wind_chill":48.6,"heat_index":48.6,"pressure":30,"precip_rate":0,"precip_total":0,"humidity":63,"wind_dir":320},{"station":"KCAMALIB62","date":"2022-01-31 03:09:00","temperature":47.8,"wind_speed":0.7,"wind_gust":1.1,"dew_point":35.9,"wind_chill":47.8,"heat_index":47.8,"pressure":30,"precip_rate":0,"precip_total":0,"humidity":64,"wind_dir":310},{"station":"KCAMALIB62","date":"2022-01-31 03:14:00","temperature":47.5,"wind_speed":0.7,"wind_gust":1.1,"dew_point":36.3,"wind_chill":47.5,"heat_index":47.5,"pressure":30,"precip_rate":0,"precip_total":0,"humidity":65,"wind_dir":311},{"station":"KCAMALIB62","date":"2022-01-31 03:19:00","temperature":47.3,"wind_speed":0,"wind_gust":0,"dew_point":36.3,"wind_chill":47.3,"heat_index":47.3,"pressure":30,"precip_rate":0,"precip_total":0,"humidity":66,"wind_dir":315},{"station":"KCAMALIB62","date":"2022-01-31 03:24:00","temperature":47.1,"wind_speed":0,"wind_gust":0,"dew_point":36.7,"wind_chill":47.1,"heat_index":47.1,"pressure":30,"precip_rate":0,"precip_total":0,"humidity":67,"wind_dir":308},{"station":"KCAMALIB62","date":"2022-01-31 03:29:00","temperature":47.1,"wind_speed":0.9,"wind_gust":1.1,"dew_point":37.1,"wind_chill":47.1,"heat_index":47.1,"pressure":30,"precip_rate":0,"precip_total":0,"humidity":68,"wind_dir":305},{"station":"KCAMALIB62","date":"2022-01-31 03:34:00","temperature":47.1,"wind_speed":0.2,"wind_gust":1.1,"dew_point":36.9,"wind_chill":47.1,"heat_index":47.1,"pressure":30,"precip_rate":0,"precip_total":0,"humidity":68,"wind_dir":296},{"station":"KCAMALIB62","date":"2022-01-31 03:39:00","temperature":47.1,"wind_speed":0,"wind_gust":0,"dew_point":37.1,"wind_chill":47.1,"heat_index":47.1,"pressure":30,"precip_rate":0,"precip_total":0,"humidity":68,"wind_dir":311},{"station":"KCAMALIB62","date":"2022-01-31 03:44:00","temperature":47.1,"wind_speed":0.7,"wind_gust":1.1,"dew_point":36.3,"wind_chill":47.1,"heat_index":47.1,"pressure":30,"precip_rate":0,"precip_total":0,"humidity":66,"wind_dir":303},{"station":"KCAMALIB62","date":"2022-01-31 03:49:00","temperature":47.3,"wind_speed":0,"wind_gust":0,"dew_point":36.1,"wind_chill":47.3,"heat_index":47.3,"pressure":29.99,"precip_rate":0,"precip_total":0,"humidity":65,"wind_dir":303},{"station":"KCAMALIB62","date":"2022-01-31 03:54:00","temperature":47.3,"wind_speed":0,"wind_gust":0,"dew_point":36.1,"wind_chill":47.3,"heat_index":47.3,"pressure":29.99,"precip_rate":0,"precip_total":0,"humidity":65,"wind_dir":305},{"station":"KCAMALIB62","date":"2022-01-31 03:59:00","temperature":46.9,"wind_speed":0,"wind_gust":0,"dew_point":35.8,"wind_chill":46.9,"heat_index":46.9,"pressure":29.99,"precip_rate":0,"precip_total":0,"humidity":65,"wind_dir":302},{"station":"KCAMALIB62","date":"2022-01-31 04:04:00","temperature":46.9,"wind_speed":0.7,"wind_gust":2.2,"dew_point":35.8,"wind_chill":46.9,"heat_index":46.9,"pressure":30,"precip_rate":0,"precip_total":0,"humidity":65,"wind_dir":303},{"station":"KCAMALIB62","date":"2022-01-31 04:09:00","temperature":46.9,"wind_speed":0,"wind_gust":0,"dew_point":35.8,"wind_chill":46.9,"heat_index":46.9,"pressure":29.99,"precip_rate":0,"precip_total":0,"humidity":65,"wind_dir":306},{"station":"KCAMALIB62","date":"2022-01-31 04:14:00","temperature":46.9,"wind_speed":0,"wind_gust":0,"dew_point":35.4,"wind_chill":46.9,"heat_index":46.9,"pressure":29.99,"precip_rate":0,"precip_total":0,"humidity":64,"wind_dir":305},{"station":"KCAMALIB62","date":"2022-01-31 04:19:00","temperature":46.8,"wind_speed":0,"wind_gust":0,"dew_point":34.9,"wind_chill":46.8,"heat_index":46.8,"pressure":29.99,"precip_rate":0,"precip_total":0,"humidity":63,"wind_dir":312},{"station":"KCAMALIB62","date":"2022-01-31 04:24:00","temperature":46.9,"wind_speed":0,"wind_gust":0,"dew_point":36.1,"wind_chill":46.9,"heat_index":46.9,"pressure":29.99,"precip_rate":0,"precip_total":0,"humidity":66,"wind_dir":301},{"station":"KCAMALIB62","date":"2022-01-31 04:29:00","temperature":46.9,"wind_speed":0.2,"wind_gust":1.1,"dew_point":36.1,"wind_chill":46.9,"heat_index":46.9,"pressure":29.99,"precip_rate":0,"precip_total":0,"humidity":66,"wind_dir":311},{"station":"KCAMALIB62","date":"2022-01-31 04:34:00","temperature":46.9,"wind_speed":0,"wind_gust":0,"dew_point":35.8,"wind_chill":46.9,"heat_index":46.9,"pressure":29.99,"precip_rate":0,"precip_total":0,"humidity":65,"wind_dir":302},{"station":"KCAMALIB62","date":"2022-01-31 04:39:00","temperature":46.9,"wind_speed":0,"wind_gust":0,"dew_point":36.4,"wind_chill":46.9,"heat_index":46.9,"pressure":29.99,"precip_rate":0,"precip_total":0,"humidity":67,"wind_dir":304},{"station":"KCAMALIB62","date":"2022-01-31 04:44:00","temperature":46.9,"wind_speed":1.6,"wind_gust":2.2,"dew_point":36.8,"wind_chill":46.9,"heat_index":46.9,"pressure":29.99,"precip_rate":0,"precip_total":0,"humidity":68,"wind_dir":305},{"station":"KCAMALIB62","date":"2022-01-31 04:49:00","temperature":47.8,"wind_speed":0,"wind_gust":0,"dew_point":35.8,"wind_chill":47.8,"heat_index":47.8,"pressure":29.98,"precip_rate":0,"precip_total":0,"humidity":63,"wind_dir":307},{"station":"KCAMALIB62","date":"2022-01-31 04:54:00","temperature":47.8,"wind_speed":0,"wind_gust":0,"dew_point":36.1,"wind_chill":47.8,"heat_index":47.8,"pressure":29.98,"precip_rate":0,"precip_total":0,"humidity":64,"wind_dir":308},{"station":"KCAMALIB62","date":"2022-01-31 04:59:00","temperature":48,"wind_speed":0,"wind_gust":0,"dew_point":36.4,"wind_chill":48,"heat_index":48,"pressure":29.98,"precip_rate":0,"precip_total":0,"humidity":64,"wind_dir":308},{"station":"KCAMALIB62","date":"2022-01-31 05:04:00","temperature":48.2,"wind_speed":0.7,"wind_gust":1.1,"dew_point":37,"wind_chill":48.2,"heat_index":48.2,"pressure":29.99,"precip_rate":0,"precip_total":0,"humidity":65,"wind_dir":319},{"station":"KCAMALIB62","date":"2022-01-31 05:09:00","temperature":48.2,"wind_speed":0,"wind_gust":0,"dew_point":37.3,"wind_chill":48.2,"heat_index":48.2,"pressure":29.99,"precip_rate":0,"precip_total":0,"humidity":67,"wind_dir":307},{"station":"KCAMALIB62","date":"2022-01-31 05:14:00","temperature":47.7,"wind_speed":0,"wind_gust":0,"dew_point":37.3,"wind_chill":47.7,"heat_index":47.7,"pressure":29.99,"precip_rate":0,"precip_total":0,"humidity":67,"wind_dir":304},{"station":"KCAMALIB62","date":"2022-01-31 05:19:00","temperature":48,"wind_speed":0.2,"wind_gust":1.1,"dew_point":36.6,"wind_chill":48,"heat_index":48,"pressure":29.99,"precip_rate":0,"precip_total":0,"humidity":65,"wind_dir":310},{"station":"KCAMALIB62","date":"2022-01-31 05:24:00","temperature":47.8,"wind_speed":0,"wind_gust":0,"dew_point":37.4,"wind_chill":47.8,"heat_index":47.8,"pressure":29.99,"precip_rate":0,"precip_total":0,"humidity":67,"wind_dir":305},{"station":"KCAMALIB62","date":"2022-01-31 05:29:00","temperature":48,"wind_speed":0,"wind_gust":0,"dew_point":37.2,"wind_chill":48,"heat_index":48,"pressure":29.99,"precip_rate":0,"precip_total":0,"humidity":66,"wind_dir":310},{"station":"KCAMALIB62","date":"2022-01-31 05:34:00","temperature":48,"wind_speed":0.4,"wind_gust":1.1,"dew_point":37,"wind_chill":48,"heat_index":48,"pressure":29.99,"precip_rate":0,"precip_total":0,"humidity":66,"wind_dir":311},{"station":"KCAMALIB62","date":"2022-01-31 05:39:00","temperature":47.8,"wind_speed":0,"wind_gust":0,"dew_point":36.9,"wind_chill":47.8,"heat_index":47.8,"pressure":29.99,"precip_rate":0,"precip_total":0,"humidity":66,"wind_dir":307},{"station":"KCAMALIB62","date":"2022-01-31 05:44:00","temperature":48,"wind_speed":0,"wind_gust":0,"dew_point":36.4,"wind_chill":48,"heat_index":48,"pressure":29.99,"precip_rate":0,"precip_total":0,"humidity":64,"wind_dir":307},{"station":"KCAMALIB62","date":"2022-01-31 05:49:00","temperature":47.8,"wind_speed":0,"wind_gust":0,"dew_point":36.9,"wind_chill":47.8,"heat_index":47.8,"pressure":29.99,"precip_rate":0,"precip_total":0,"humidity":66,"wind_dir":310},{"station":"KCAMALIB62","date":"2022-01-31 05:54:00","temperature":47.5,"wind_speed":0.2,"wind_gust":1.1,"dew_point":37.1,"wind_chill":47.5,"heat_index":47.5,"pressure":29.99,"precip_rate":0,"precip_total":0,"humidity":67,"wind_dir":308},{"station":"KCAMALIB62","date":"2022-01-31 05:59:00","temperature":47.1,"wind_speed":0,"wind_gust":0,"dew_point":37.5,"wind_chill":47.1,"heat_index":47.1,"pressure":29.99,"precip_rate":0,"precip_total":0,"humidity":69,"wind_dir":311},{"station":"KCAMALIB62","date":"2022-01-31 06:04:00","temperature":47.5,"wind_speed":0.2,"wind_gust":1.1,"dew_point":37.8,"wind_chill":47.5,"heat_index":47.5,"pressure":29.99,"precip_rate":0,"precip_total":0,"humidity":69,"wind_dir":309},{"station":"KCAMALIB62","date":"2022-01-31 06:09:00","temperature":47.5,"wind_speed":0.2,"wind_gust":1.1,"dew_point":37.8,"wind_chill":47.5,"heat_index":47.5,"pressure":30,"precip_rate":0,"precip_total":0,"humidity":69,"wind_dir":308},{"station":"KCAMALIB62","date":"2022-01-31 06:14:00","temperature":47.5,"wind_speed":0.7,"wind_gust":1.1,"dew_point":38.2,"wind_chill":47.5,"heat_index":47.5,"pressure":29.99,"precip_rate":0,"precip_total":0,"humidity":70,"wind_dir":305},{"station":"KCAMALIB62","date":"2022-01-31 06:19:00","temperature":47.3,"wind_speed":0,"wind_gust":0,"dew_point":38,"wind_chill":47.3,"heat_index":47.3,"pressure":30,"precip_rate":0,"precip_total":0,"humidity":70,"wind_dir":309},{"station":"KCAMALIB62","date":"2022-01-31 06:24:00","temperature":47.1,"wind_speed":0.7,"wind_gust":1.1,"dew_point":37.8,"wind_chill":47.1,"heat_index":47.1,"pressure":30,"precip_rate":0,"precip_total":0,"humidity":70,"wind_dir":325},{"station":"KCAMALIB62","date":"2022-01-31 06:29:00","temperature":47.5,"wind_speed":0.2,"wind_gust":1.1,"dew_point":38.2,"wind_chill":47.5,"heat_index":47.5,"pressure":29.99,"precip_rate":0,"precip_total":0,"humidity":70,"wind_dir":317},{"station":"KCAMALIB62","date":"2022-01-31 06:34:00","temperature":47.5,"wind_speed":1.3,"wind_gust":2.2,"dew_point":38,"wind_chill":47.5,"heat_index":47.5,"pressure":30,"precip_rate":0,"precip_total":0,"humidity":70,"wind_dir":323},{"station":"KCAMALIB62","date":"2022-01-31 06:39:00","temperature":47.7,"wind_speed":0.4,"wind_gust":1.1,"dew_point":38,"wind_chill":47.7,"heat_index":47.7,"pressure":29.99,"precip_rate":0,"precip_total":0,"humidity":69,"wind_dir":320},{"station":"KCAMALIB62","date":"2022-01-31 06:44:00","temperature":47.8,"wind_speed":0,"wind_gust":0,"dew_point":38.1,"wind_chill":47.8,"heat_index":47.8,"pressure":29.99,"precip_rate":0,"precip_total":0,"humidity":69,"wind_dir":322},{"station":"KCAMALIB62","date":"2022-01-31 06:49:00","temperature":47.8,"wind_speed":0.7,"wind_gust":1.1,"dew_point":38.1,"wind_chill":47.8,"heat_index":47.8,"pressure":29.99,"precip_rate":0,"precip_total":0,"humidity":69,"wind_dir":312},{"station":"KCAMALIB62","date":"2022-01-31 06:54:00","temperature":47.8,"wind_speed":0.7,"wind_gust":1.1,"dew_point":38.1,"wind_chill":47.8,"heat_index":47.8,"pressure":29.99,"precip_rate":0,"precip_total":0,"humidity":69,"wind_dir":311},{"station":"KCAMALIB62","date":"2022-01-31 06:59:00","temperature":48,"wind_speed":0.2,"wind_gust":1.1,"dew_point":37.8,"wind_chill":48,"heat_index":48,"pressure":29.99,"precip_rate":0,"precip_total":0,"humidity":68,"wind_dir":305},{"station":"KCAMALIB62","date":"2022-01-31 07:04:00","temperature":48.2,"wind_speed":0,"wind_gust":0,"dew_point":38.1,"wind_chill":48.2,"heat_index":48.2,"pressure":29.99,"precip_rate":0,"precip_total":0,"humidity":68,"wind_dir":307},{"station":"KCAMALIB62","date":"2022-01-31 07:09:00","temperature":48.2,"wind_speed":0.2,"wind_gust":1.1,"dew_point":38.1,"wind_chill":48.2,"heat_index":48.2,"pressure":29.99,"precip_rate":0,"precip_total":0,"humidity":68,"wind_dir":308},{"station":"KCAMALIB62","date":"2022-01-31 07:14:00","temperature":48.4,"wind_speed":0.2,"wind_gust":1.1,"dew_point":37.8,"wind_chill":48.4,"heat_index":48.4,"pressure":30,"precip_rate":0,"precip_total":0,"humidity":67,"wind_dir":325},{"station":"KCAMALIB62","date":"2022-01-31 07:19:00","temperature":48.7,"wind_speed":0.2,"wind_gust":1.1,"dew_point":38.2,"wind_chill":48.7,"heat_index":48.7,"pressure":30,"precip_rate":0,"precip_total":0,"humidity":67,"wind_dir":321},{"station":"KCAMALIB62","date":"2022-01-31 07:24:00","temperature":48.6,"wind_speed":0.2,"wind_gust":1.1,"dew_point":37.8,"wind_chill":48.6,"heat_index":48.6,"pressure":30,"precip_rate":0,"precip_total":0,"humidity":66,"wind_dir":316},{"station":"KCAMALIB62","date":"2022-01-31 07:29:00","temperature":48.7,"wind_speed":0.9,"wind_gust":1.1,"dew_point":37.9,"wind_chill":48.7,"heat_index":48.7,"pressure":30,"precip_rate":0,"precip_total":0,"humidity":66,"wind_dir":308},{"station":"KCAMALIB62","date":"2022-01-31 07:34:00","temperature":49.1,"wind_speed":0.7,"wind_gust":1.1,"dew_point":38.6,"wind_chill":49.1,"heat_index":49.1,"pressure":29.99,"precip_rate":0,"precip_total":0,"humidity":67,"wind_dir":327},{"station":"KCAMALIB62","date":"2022-01-31 07:39:00","temperature":49.6,"wind_speed":0.7,"wind_gust":1.1,"dew_point":38.6,"wind_chill":49.6,"heat_index":49.6,"pressure":30,"precip_rate":0,"precip_total":0,"humidity":67,"wind_dir":315},{"station":"KCAMALIB62","date":"2022-01-31 07:43:00","temperature":50.2,"wind_speed":0.7,"wind_gust":1.1,"dew_point":38.9,"wind_chill":50.2,"heat_index":50.2,"pressure":30,"precip_rate":0,"precip_total":0,"humidity":65,"wind_dir":321},{"station":"KCAMALIB62","date":"2022-01-31 07:49:00","temperature":50.4,"wind_speed":0,"wind_gust":0,"dew_point":39.5,"wind_chill":50.4,"heat_index":50.4,"pressure":29.99,"precip_rate":0,"precip_total":0,"humidity":66,"wind_dir":313},{"station":"KCAMALIB62","date":"2022-01-31 07:54:00","temperature":51.3,"wind_speed":0.9,"wind_gust":1.1,"dew_point":39.2,"wind_chill":51.3,"heat_index":51.3,"pressure":30,"precip_rate":0,"precip_total":0,"humidity":65,"wind_dir":324},{"station":"KCAMALIB62","date":"2022-01-31 07:59:00","temperature":53.1,"wind_speed":0.7,"wind_gust":1.1,"dew_point":40.4,"wind_chill":53.1,"heat_index":53.1,"pressure":30,"precip_rate":0,"precip_total":0,"humidity":63,"wind_dir":313},{"station":"KCAMALIB62","date":"2022-01-31 08:03:00","temperature":54,"wind_speed":0,"wind_gust":0,"dew_point":40.7,"wind_chill":54,"heat_index":54,"pressure":29.99,"precip_rate":0,"precip_total":0,"humidity":61,"wind_dir":312},{"station":"KCAMALIB62","date":"2022-01-31 08:09:00","temperature":54.7,"wind_speed":0,"wind_gust":0,"dew_point":41.1,"wind_chill":54.7,"heat_index":54.7,"pressure":30,"precip_rate":0,"precip_total":0,"humidity":61,"wind_dir":312},{"station":"KCAMALIB62","date":"2022-01-31 08:14:00","temperature":56.1,"wind_speed":0.4,"wind_gust":1.1,"dew_point":39.9,"wind_chill":56.1,"heat_index":56.1,"pressure":30,"precip_rate":0,"precip_total":0,"humidity":55,"wind_dir":320},{"station":"KCAMALIB62","date":"2022-01-31 08:19:00","temperature":57.9,"wind_speed":0,"wind_gust":0,"dew_point":39.4,"wind_chill":57.9,"heat_index":57.9,"pressure":30,"precip_rate":0,"precip_total":0,"humidity":52,"wind_dir":297},{"station":"KCAMALIB62","date":"2022-01-31 08:24:00","temperature":58.6,"wind_speed":0,"wind_gust":0,"dew_point":40,"wind_chill":58.6,"heat_index":58.6,"pressure":30,"precip_rate":0,"precip_total":0,"humidity":50,"wind_dir":299},{"station":"KCAMALIB62","date":"2022-01-31 08:29:00","temperature":58.6,"wind_speed":0,"wind_gust":0,"dew_point":40.3,"wind_chill":58.6,"heat_index":58.6,"pressure":30,"precip_rate":0,"precip_total":0,"humidity":51,"wind_dir":296},{"station":"KCAMALIB62","date":"2022-01-31 08:34:00","temperature":58.3,"wind_speed":0,"wind_gust":0,"dew_point":40.9,"wind_chill":58.3,"heat_index":58.3,"pressure":30,"precip_rate":0,"precip_total":0,"humidity":53,"wind_dir":316},{"station":"KCAMALIB62","date":"2022-01-31 08:39:00","temperature":61.7,"wind_speed":0,"wind_gust":0,"dew_point":40.2,"wind_chill":61.7,"heat_index":61.7,"pressure":30.01,"precip_rate":0,"precip_total":0,"humidity":49,"wind_dir":316},{"station":"KCAMALIB62","date":"2022-01-31 08:44:00","temperature":62.6,"wind_speed":0,"wind_gust":0,"dew_point":41.2,"wind_chill":62.6,"heat_index":62.6,"pressure":30.01,"precip_rate":0,"precip_total":0,"humidity":46,"wind_dir":310},{"station":"KCAMALIB62","date":"2022-01-31 08:49:00","temperature":61.7,"wind_speed":0,"wind_gust":0,"dew_point":41.3,"wind_chill":61.7,"heat_index":61.7,"pressure":30.01,"precip_rate":0,"precip_total":0,"humidity":47,"wind_dir":308},{"station":"KCAMALIB62","date":"2022-01-31 08:54:00","temperature":61.7,"wind_speed":1.3,"wind_gust":2.2,"dew_point":41.3,"wind_chill":61.7,"heat_index":61.7,"pressure":30.01,"precip_rate":0,"precip_total":0,"humidity":47,"wind_dir":214},{"station":"KCAMALIB62","date":"2022-01-31 08:59:00","temperature":61.7,"wind_speed":1.1,"wind_gust":1.1,"dew_point":41.9,"wind_chill":61.7,"heat_index":61.7,"pressure":30.02,"precip_rate":0,"precip_total":0,"humidity":49,"wind_dir":313},{"station":"KCAMALIB62","date":"2022-01-31 09:04:00","temperature":60.6,"wind_speed":0.4,"wind_gust":1.1,"dew_point":42.4,"wind_chill":60.6,"heat_index":60.6,"pressure":30.01,"precip_rate":0,"precip_total":0,"humidity":53,"wind_dir":357},{"station":"KCAMALIB62","date":"2022-01-31 09:09:00","temperature":58.1,"wind_speed":0.2,"wind_gust":1.1,"dew_point":41.6,"wind_chill":58.1,"heat_index":58.1,"pressure":30.02,"precip_rate":0,"precip_total":0,"humidity":55,"wind_dir":288},{"station":"KCAMALIB62","date":"2022-01-31 09:14:00","temperature":58.3,"wind_speed":0.7,"wind_gust":1.1,"dew_point":42.3,"wind_chill":58.3,"heat_index":58.3,"pressure":30.01,"precip_rate":0,"precip_total":0,"humidity":56,"wind_dir":302},{"station":"KCAMALIB62","date":"2022-01-31 09:19:00","temperature":59.2,"wind_speed":0.4,"wind_gust":1.1,"dew_point":42.6,"wind_chill":59.2,"heat_index":59.2,"pressure":30.01,"precip_rate":0,"precip_total":0,"humidity":55,"wind_dir":48},{"station":"KCAMALIB62","date":"2022-01-31 09:24:00","temperature":59.9,"wind_speed":1.8,"wind_gust":2.2,"dew_point":42.7,"wind_chill":59.9,"heat_index":59.9,"pressure":30.02,"precip_rate":0,"precip_total":0,"humidity":53,"wind_dir":34},{"station":"KCAMALIB62","date":"2022-01-31 09:29:00","temperature":60.4,"wind_speed":0.7,"wind_gust":1.1,"dew_point":42.5,"wind_chill":60.4,"heat_index":60.4,"pressure":30.02,"precip_rate":0,"precip_total":0,"humidity":53,"wind_dir":301},{"station":"KCAMALIB62","date":"2022-01-31 09:34:00","temperature":59.5,"wind_speed":0.9,"wind_gust":1.1,"dew_point":42.4,"wind_chill":59.5,"heat_index":59.5,"pressure":30.02,"precip_rate":0,"precip_total":0,"humidity":53,"wind_dir":273},{"station":"KCAMALIB62","date":"2022-01-31 09:39:00","temperature":59.5,"wind_speed":0.2,"wind_gust":1.1,"dew_point":41.9,"wind_chill":59.5,"heat_index":59.5,"pressure":30.02,"precip_rate":0,"precip_total":0,"humidity":52,"wind_dir":294},{"station":"KCAMALIB62","date":"2022-01-31 09:44:00","temperature":59.4,"wind_speed":0.2,"wind_gust":1.1,"dew_point":42.3,"wind_chill":59.4,"heat_index":59.4,"pressure":30.02,"precip_rate":0,"precip_total":0,"humidity":53,"wind_dir":298},{"station":"KCAMALIB62","date":"2022-01-31 09:49:00","temperature":58.8,"wind_speed":1.1,"wind_gust":1.1,"dew_point":42.2,"wind_chill":58.8,"heat_index":58.8,"pressure":30.02,"precip_rate":0,"precip_total":0,"humidity":55,"wind_dir":336},{"station":"KCAMALIB62","date":"2022-01-31 09:54:00","temperature":57.9,"wind_speed":0.7,"wind_gust":1.1,"dew_point":41.8,"wind_chill":57.9,"heat_index":57.9,"pressure":30.02,"precip_rate":0,"precip_total":0,"humidity":55,"wind_dir":222},{"station":"KCAMALIB62","date":"2022-01-31 09:59:00","temperature":57.9,"wind_speed":0.9,"wind_gust":1.1,"dew_point":41.6,"wind_chill":57.9,"heat_index":57.9,"pressure":30.01,"precip_rate":0,"precip_total":0,"humidity":55,"wind_dir":278},{"station":"KCAMALIB62","date":"2022-01-31 10:04:00","temperature":57.9,"wind_speed":0.7,"wind_gust":1.1,"dew_point":41.4,"wind_chill":57.9,"heat_index":57.9,"pressure":30.02,"precip_rate":0,"precip_total":0,"humidity":54,"wind_dir":272},{"station":"KCAMALIB62","date":"2022-01-31 10:09:00","temperature":57.9,"wind_speed":1.1,"wind_gust":1.1,"dew_point":40.9,"wind_chill":57.9,"heat_index":57.9,"pressure":30.02,"precip_rate":0,"precip_total":0,"humidity":53,"wind_dir":266},{"station":"KCAMALIB62","date":"2022-01-31 10:14:00","temperature":57.9,"wind_speed":0,"wind_gust":0,"dew_point":41.2,"wind_chill":57.9,"heat_index":57.9,"pressure":30.01,"precip_rate":0,"precip_total":0,"humidity":54,"wind_dir":326},{"station":"KCAMALIB62","date":"2022-01-31 10:19:00","temperature":58.5,"wind_speed":0.2,"wind_gust":1.1,"dew_point":41.1,"wind_chill":58.5,"heat_index":58.5,"pressure":30.01,"precip_rate":0,"precip_total":0,"humidity":53,"wind_dir":312},{"station":"KCAMALIB62","date":"2022-01-31 10:24:00","temperature":58.5,"wind_speed":0.7,"wind_gust":1.1,"dew_point":41.4,"wind_chill":58.5,"heat_index":58.5,"pressure":30.01,"precip_rate":0,"precip_total":0,"humidity":53,"wind_dir":178},{"station":"KCAMALIB62","date":"2022-01-31 10:29:00","temperature":58.5,"wind_speed":0.9,"wind_gust":1.1,"dew_point":40.9,"wind_chill":58.5,"heat_index":58.5,"pressure":30.01,"precip_rate":0,"precip_total":0,"humidity":52,"wind_dir":2},{"station":"KCAMALIB62","date":"2022-01-31 10:34:00","temperature":58.3,"wind_speed":0.4,"wind_gust":1.1,"dew_point":40.3,"wind_chill":58.3,"heat_index":58.3,"pressure":30,"precip_rate":0,"precip_total":0,"humidity":51,"wind_dir":324},{"station":"KCAMALIB62","date":"2022-01-31 10:39:00","temperature":58.8,"wind_speed":0.9,"wind_gust":1.1,"dew_point":40.5,"wind_chill":58.8,"heat_index":58.8,"pressure":30,"precip_rate":0,"precip_total":0,"humidity":51,"wind_dir":335},{"station":"KCAMALIB62","date":"2022-01-31 10:44:00","temperature":58.8,"wind_speed":1.1,"wind_gust":2.2,"dew_point":42.7,"wind_chill":58.8,"heat_index":58.8,"pressure":30,"precip_rate":0,"precip_total":0,"humidity":56,"wind_dir":232},{"station":"KCAMALIB62","date":"2022-01-31 10:49:00","temperature":57.7,"wind_speed":0.7,"wind_gust":1.1,"dew_point":42.9,"wind_chill":57.7,"heat_index":57.7,"pressure":30,"precip_rate":0,"precip_total":0,"humidity":58,"wind_dir":269},{"station":"KCAMALIB62","date":"2022-01-31 10:54:00","temperature":57.9,"wind_speed":0.7,"wind_gust":1.1,"dew_point":43.7,"wind_chill":57.9,"heat_index":57.9,"pressure":30,"precip_rate":0,"precip_total":0,"humidity":59,"wind_dir":324},{"station":"KCAMALIB62","date":"2022-01-31 10:59:00","temperature":58.5,"wind_speed":1.1,"wind_gust":2.2,"dew_point":43.8,"wind_chill":58.5,"heat_index":58.5,"pressure":30.01,"precip_rate":0,"precip_total":0,"humidity":59,"wind_dir":339},{"station":"KCAMALIB62","date":"2022-01-31 11:04:00","temperature":58.8,"wind_speed":0.9,"wind_gust":1.1,"dew_point":43.1,"wind_chill":58.8,"heat_index":58.8,"pressure":30,"precip_rate":0,"precip_total":0,"humidity":56,"wind_dir":312},{"station":"KCAMALIB62","date":"2022-01-31 11:09:00","temperature":58.6,"wind_speed":1.1,"wind_gust":1.1,"dew_point":43.6,"wind_chill":58.6,"heat_index":58.6,"pressure":30,"precip_rate":0,"precip_total":0,"humidity":58,"wind_dir":334},{"station":"KCAMALIB62","date":"2022-01-31 11:14:00","temperature":58.3,"wind_speed":1.1,"wind_gust":2.2,"dew_point":44,"wind_chill":58.3,"heat_index":58.3,"pressure":30,"precip_rate":0,"precip_total":0,"humidity":60,"wind_dir":331},{"station":"KCAMALIB62","date":"2022-01-31 11:19:00","temperature":57.4,"wind_speed":0.7,"wind_gust":1.1,"dew_point":43.9,"wind_chill":57.4,"heat_index":57.4,"pressure":30,"precip_rate":0,"precip_total":0,"humidity":61,"wind_dir":279},{"station":"KCAMALIB62","date":"2022-01-31 11:24:00","temperature":57.4,"wind_speed":0.9,"wind_gust":1.1,"dew_point":44.1,"wind_chill":57.4,"heat_index":57.4,"pressure":30,"precip_rate":0,"precip_total":0,"humidity":61,"wind_dir":320},{"station":"KCAMALIB62","date":"2022-01-31 11:29:00","temperature":57.4,"wind_speed":1.8,"wind_gust":2.2,"dew_point":44.5,"wind_chill":57.4,"heat_index":57.4,"pressure":29.99,"precip_rate":0,"precip_total":0,"humidity":62,"wind_dir":12},{"station":"KCAMALIB62","date":"2022-01-31 11:34:00","temperature":57,"wind_speed":0.9,"wind_gust":1.1,"dew_point":44.5,"wind_chill":57,"heat_index":57,"pressure":29.99,"precip_rate":0,"precip_total":0,"humidity":63,"wind_dir":318},{"station":"KCAMALIB62","date":"2022-01-31 11:39:00","temperature":57.6,"wind_speed":0.9,"wind_gust":1.1,"dew_point":44.7,"wind_chill":57.6,"heat_index":57.6,"pressure":29.99,"precip_rate":0,"precip_total":0,"humidity":63,"wind_dir":303},{"station":"KCAMALIB62","date":"2022-01-31 11:44:00","temperature":58.1,"wind_speed":0.9,"wind_gust":1.1,"dew_point":45.1,"wind_chill":58.1,"heat_index":58.1,"pressure":29.98,"precip_rate":0,"precip_total":0,"humidity":63,"wind_dir":324},{"station":"KCAMALIB62","date":"2022-01-31 11:49:00","temperature":58.5,"wind_speed":1.1,"wind_gust":1.1,"dew_point":43.3,"wind_chill":58.5,"heat_index":58.5,"pressure":29.98,"precip_rate":0,"precip_total":0,"humidity":57,"wind_dir":357},{"station":"KCAMALIB62","date":"2022-01-31 11:54:00","temperature":59,"wind_speed":1.3,"wind_gust":2.2,"dew_point":42.9,"wind_chill":59,"heat_index":59,"pressure":29.98,"precip_rate":0,"precip_total":0,"humidity":55,"wind_dir":307},{"station":"KCAMALIB62","date":"2022-01-31 11:59:00","temperature":60.3,"wind_speed":1.3,"wind_gust":2.2,"dew_point":43.3,"wind_chill":60.3,"heat_index":60.3,"pressure":29.98,"precip_rate":0,"precip_total":0,"humidity":55,"wind_dir":343},{"station":"KCAMALIB62","date":"2022-01-31 12:04:00","temperature":60.1,"wind_speed":1.3,"wind_gust":2.2,"dew_point":44,"wind_chill":60.1,"heat_index":60.1,"pressure":29.97,"precip_rate":0,"precip_total":0,"humidity":56,"wind_dir":305},{"station":"KCAMALIB62","date":"2022-01-31 12:09:00","temperature":59.5,"wind_speed":2,"wind_gust":2.2,"dew_point":43.8,"wind_chill":59.5,"heat_index":59.5,"pressure":29.97,"precip_rate":0,"precip_total":0,"humidity":56,"wind_dir":351},{"station":"KCAMALIB62","date":"2022-01-31 12:14:00","temperature":59,"wind_speed":1.3,"wind_gust":2.2,"dew_point":43.3,"wind_chill":59,"heat_index":59,"pressure":29.96,"precip_rate":0,"precip_total":0,"humidity":56,"wind_dir":95},{"station":"KCAMALIB62","date":"2022-01-31 12:19:00","temperature":59.5,"wind_speed":1.6,"wind_gust":2.2,"dew_point":42.9,"wind_chill":59.5,"heat_index":59.5,"pressure":29.95,"precip_rate":0,"precip_total":0,"humidity":55,"wind_dir":340},{"station":"KCAMALIB62","date":"2022-01-31 12:24:00","temperature":60.3,"wind_speed":1.8,"wind_gust":3.4,"dew_point":46.2,"wind_chill":60.3,"heat_index":60.3,"pressure":29.95,"precip_rate":0,"precip_total":0,"humidity":60,"wind_dir":356},{"station":"KCAMALIB62","date":"2022-01-31 12:29:00","temperature":59.9,"wind_speed":1.3,"wind_gust":2.2,"dew_point":46.7,"wind_chill":59.9,"heat_index":59.9,"pressure":29.95,"precip_rate":0,"precip_total":0,"humidity":63,"wind_dir":354},{"station":"KCAMALIB62","date":"2022-01-31 12:34:00","temperature":60.3,"wind_speed":2.7,"wind_gust":4.5,"dew_point":48.1,"wind_chill":60.3,"heat_index":60.3,"pressure":29.94,"precip_rate":0,"precip_total":0,"humidity":64,"wind_dir":216},{"station":"KCAMALIB62","date":"2022-01-31 12:38:00","temperature":60.6,"wind_speed":2.2,"wind_gust":2.2,"dew_point":47.9,"wind_chill":60.6,"heat_index":60.6,"pressure":29.95,"precip_rate":0,"precip_total":0,"humidity":63,"wind_dir":156},{"station":"KCAMALIB62","date":"2022-01-31 12:44:00","temperature":60.4,"wind_speed":1.1,"wind_gust":1.1,"dew_point":47.3,"wind_chill":60.4,"heat_index":60.4,"pressure":29.95,"precip_rate":0,"precip_total":0,"humidity":63,"wind_dir":288},{"station":"KCAMALIB62","date":"2022-01-31 12:49:00","temperature":60.6,"wind_speed":0.9,"wind_gust":1.1,"dew_point":48.2,"wind_chill":60.6,"heat_index":60.6,"pressure":29.94,"precip_rate":0,"precip_total":0,"humidity":64,"wind_dir":319},{"station":"KCAMALIB62","date":"2022-01-31 12:54:00","temperature":60.6,"wind_speed":2,"wind_gust":2.2,"dew_point":48.2,"wind_chill":60.6,"heat_index":60.6,"pressure":29.94,"precip_rate":0,"precip_total":0,"humidity":64,"wind_dir":341},{"station":"KCAMALIB62","date":"2022-01-31 12:59:00","temperature":59.9,"wind_speed":1.1,"wind_gust":2.2,"dew_point":48.5,"wind_chill":59.9,"heat_index":59.9,"pressure":29.94,"precip_rate":0,"precip_total":0,"humidity":67,"wind_dir":18},{"station":"KCAMALIB62","date":"2022-01-31 13:04:00","temperature":59.2,"wind_speed":1.3,"wind_gust":2.2,"dew_point":49,"wind_chill":59.2,"heat_index":59.2,"pressure":29.93,"precip_rate":0,"precip_total":0,"humidity":69,"wind_dir":328},{"station":"KCAMALIB62","date":"2022-01-31 13:09:00","temperature":59,"wind_speed":1.8,"wind_gust":2.2,"dew_point":47.7,"wind_chill":59,"heat_index":59,"pressure":29.93,"precip_rate":0,"precip_total":0,"humidity":66,"wind_dir":127},{"station":"KCAMALIB62","date":"2022-01-31 13:14:00","temperature":59.5,"wind_speed":0,"wind_gust":0,"dew_point":47.2,"wind_chill":59.5,"heat_index":59.5,"pressure":29.93,"precip_rate":0,"precip_total":0,"humidity":64,"wind_dir":307},{"station":"KCAMALIB62","date":"2022-01-31 13:19:00","temperature":59.5,"wind_speed":1.1,"wind_gust":2.2,"dew_point":47.3,"wind_chill":59.5,"heat_index":59.5,"pressure":29.92,"precip_rate":0,"precip_total":0,"humidity":64,"wind_dir":298},{"station":"KCAMALIB62","date":"2022-01-31 13:24:00","temperature":59.5,"wind_speed":0.9,"wind_gust":1.1,"dew_point":47.3,"wind_chill":59.5,"heat_index":59.5,"pressure":29.92,"precip_rate":0,"precip_total":0,"humidity":64,"wind_dir":356},{"station":"KCAMALIB62","date":"2022-01-31 13:29:00","temperature":59.2,"wind_speed":1.1,"wind_gust":1.1,"dew_point":48.5,"wind_chill":59.2,"heat_index":59.2,"pressure":29.91,"precip_rate":0,"precip_total":0,"humidity":68,"wind_dir":332},{"station":"KCAMALIB62","date":"2022-01-31 13:34:00","temperature":59,"wind_speed":1.3,"wind_gust":2.2,"dew_point":48.8,"wind_chill":59,"heat_index":59,"pressure":29.91,"precip_rate":0,"precip_total":0,"humidity":69,"wind_dir":300},{"station":"KCAMALIB62","date":"2022-01-31 13:39:00","temperature":59.2,"wind_speed":1.8,"wind_gust":2.2,"dew_point":48.7,"wind_chill":59.2,"heat_index":59.2,"pressure":29.9,"precip_rate":0,"precip_total":0,"humidity":69,"wind_dir":31},{"station":"KCAMALIB62","date":"2022-01-31 13:44:00","temperature":59.7,"wind_speed":1.1,"wind_gust":2.2,"dew_point":47,"wind_chill":59.7,"heat_index":59.7,"pressure":29.89,"precip_rate":0,"precip_total":0,"humidity":64,"wind_dir":263},{"station":"KCAMALIB62","date":"2022-01-31 13:49:00","temperature":60.8,"wind_speed":1.6,"wind_gust":2.2,"dew_point":47.7,"wind_chill":60.8,"heat_index":60.8,"pressure":29.89,"precip_rate":0,"precip_total":0,"humidity":62,"wind_dir":278},{"station":"KCAMALIB62","date":"2022-01-31 13:54:00","temperature":61.2,"wind_speed":1.1,"wind_gust":2.2,"dew_point":48.1,"wind_chill":61.2,"heat_index":61.2,"pressure":29.89,"precip_rate":0,"precip_total":0,"humidity":62,"wind_dir":337},{"station":"KCAMALIB62","date":"2022-01-31 13:59:00","temperature":61.2,"wind_speed":1.8,"wind_gust":2.2,"dew_point":49.8,"wind_chill":61.2,"heat_index":61.2,"pressure":29.89,"precip_rate":0,"precip_total":0,"humidity":69,"wind_dir":55},{"station":"KCAMALIB62","date":"2022-01-31 14:04:00","temperature":59.5,"wind_speed":2,"wind_gust":2.2,"dew_point":49.6,"wind_chill":59.5,"heat_index":59.5,"pressure":29.89,"precip_rate":0,"precip_total":0,"humidity":70,"wind_dir":240},{"station":"KCAMALIB62","date":"2022-01-31 14:09:00","temperature":59.5,"wind_speed":1.3,"wind_gust":2.2,"dew_point":49.2,"wind_chill":59.5,"heat_index":59.5,"pressure":29.9,"precip_rate":0,"precip_total":0,"humidity":70,"wind_dir":293},{"station":"KCAMALIB62","date":"2022-01-31 14:14:00","temperature":59.9,"wind_speed":1.3,"wind_gust":2.2,"dew_point":48.9,"wind_chill":59.9,"heat_index":59.9,"pressure":29.9,"precip_rate":0,"precip_total":0,"humidity":67,"wind_dir":24},{"station":"KCAMALIB62","date":"2022-01-31 14:19:00","temperature":60.1,"wind_speed":1.3,"wind_gust":2.2,"dew_point":47,"wind_chill":60.1,"heat_index":60.1,"pressure":29.9,"precip_rate":0,"precip_total":0,"humidity":62,"wind_dir":7},{"station":"KCAMALIB62","date":"2022-01-31 14:24:00","temperature":60.1,"wind_speed":0.9,"wind_gust":1.1,"dew_point":47.5,"wind_chill":60.1,"heat_index":60.1,"pressure":29.91,"precip_rate":0,"precip_total":0,"humidity":63,"wind_dir":287},{"station":"KCAMALIB62","date":"2022-01-31 14:29:00","temperature":61,"wind_speed":1.6,"wind_gust":2.2,"dew_point":49.2,"wind_chill":61,"heat_index":61,"pressure":29.91,"precip_rate":0,"precip_total":0,"humidity":66,"wind_dir":253},{"station":"KCAMALIB62","date":"2022-01-31 14:34:00","temperature":61.2,"wind_speed":1.1,"wind_gust":1.1,"dew_point":49.3,"wind_chill":61.2,"heat_index":61.2,"pressure":29.91,"precip_rate":0,"precip_total":0,"humidity":65,"wind_dir":280},{"station":"KCAMALIB62","date":"2022-01-31 14:39:00","temperature":60.6,"wind_speed":0.7,"wind_gust":1.1,"dew_point":49,"wind_chill":60.6,"heat_index":60.6,"pressure":29.9,"precip_rate":0,"precip_total":0,"humidity":66,"wind_dir":358},{"station":"KCAMALIB62","date":"2022-01-31 14:44:00","temperature":61,"wind_speed":0.7,"wind_gust":1.1,"dew_point":48.4,"wind_chill":61,"heat_index":61,"pressure":29.89,"precip_rate":0,"precip_total":0,"humidity":64,"wind_dir":290},{"station":"KCAMALIB62","date":"2022-01-31 14:49:00","temperature":61.3,"wind_speed":0.7,"wind_gust":1.1,"dew_point":47.2,"wind_chill":61.3,"heat_index":61.3,"pressure":29.89,"precip_rate":0,"precip_total":0,"humidity":60,"wind_dir":307},{"station":"KCAMALIB62","date":"2022-01-31 14:54:00","temperature":61.5,"wind_speed":0.7,"wind_gust":1.1,"dew_point":49.6,"wind_chill":61.5,"heat_index":61.5,"pressure":29.89,"precip_rate":0,"precip_total":0,"humidity":65,"wind_dir":289},{"station":"KCAMALIB62","date":"2022-01-31 14:59:00","temperature":61.3,"wind_speed":1.1,"wind_gust":2.2,"dew_point":50.6,"wind_chill":61.3,"heat_index":61.3,"pressure":29.89,"precip_rate":0,"precip_total":0,"humidity":69,"wind_dir":262},{"station":"KCAMALIB62","date":"2022-01-31 15:04:00","temperature":59.9,"wind_speed":2.7,"wind_gust":3.4,"dew_point":50.7,"wind_chill":59.9,"heat_index":59.9,"pressure":29.89,"precip_rate":0,"precip_total":0,"humidity":73,"wind_dir":262},{"station":"KCAMALIB62","date":"2022-01-31 15:09:00","temperature":58.5,"wind_speed":1.3,"wind_gust":2.2,"dew_point":49.9,"wind_chill":58.5,"heat_index":58.5,"pressure":29.89,"precip_rate":0,"precip_total":0,"humidity":73,"wind_dir":281},{"station":"KCAMALIB62","date":"2022-01-31 15:14:00","temperature":58.3,"wind_speed":0.9,"wind_gust":1.1,"dew_point":50,"wind_chill":58.3,"heat_index":58.3,"pressure":29.9,"precip_rate":0,"precip_total":0,"humidity":74,"wind_dir":289},{"station":"KCAMALIB62","date":"2022-01-31 15:19:00","temperature":58.3,"wind_speed":1.8,"wind_gust":2.2,"dew_point":50.4,"wind_chill":58.3,"heat_index":58.3,"pressure":29.9,"precip_rate":0,"precip_total":0,"humidity":75,"wind_dir":250},{"station":"KCAMALIB62","date":"2022-01-31 15:24:00","temperature":58.3,"wind_speed":0.7,"wind_gust":1.1,"dew_point":50,"wind_chill":58.3,"heat_index":58.3,"pressure":29.89,"precip_rate":0,"precip_total":0,"humidity":74,"wind_dir":279},{"station":"KCAMALIB62","date":"2022-01-31 15:29:00","temperature":58.6,"wind_speed":1.1,"wind_gust":1.1,"dew_point":50,"wind_chill":58.6,"heat_index":58.6,"pressure":29.89,"precip_rate":0,"precip_total":0,"humidity":74,"wind_dir":289},{"station":"KCAMALIB62","date":"2022-01-31 15:34:00","temperature":58.6,"wind_speed":0.9,"wind_gust":1.1,"dew_point":50,"wind_chill":58.6,"heat_index":58.6,"pressure":29.89,"precip_rate":0,"precip_total":0,"humidity":73,"wind_dir":296},{"station":"KCAMALIB62","date":"2022-01-31 15:39:00","temperature":58.6,"wind_speed":2.2,"wind_gust":3.4,"dew_point":50.6,"wind_chill":58.6,"heat_index":58.6,"pressure":29.89,"precip_rate":0,"precip_total":0,"humidity":75,"wind_dir":293},{"station":"KCAMALIB62","date":"2022-01-31 15:44:00","temperature":58.5,"wind_speed":2.7,"wind_gust":3.4,"dew_point":50.2,"wind_chill":58.5,"heat_index":58.5,"pressure":29.89,"precip_rate":0,"precip_total":0,"humidity":74,"wind_dir":282},{"station":"KCAMALIB62","date":"2022-01-31 15:49:00","temperature":58.1,"wind_speed":1.6,"wind_gust":2.2,"dew_point":49.5,"wind_chill":58.1,"heat_index":58.1,"pressure":29.89,"precip_rate":0,"precip_total":0,"humidity":73,"wind_dir":293},{"station":"KCAMALIB62","date":"2022-01-31 15:54:00","temperature":58.6,"wind_speed":2.2,"wind_gust":3.4,"dew_point":51.1,"wind_chill":58.6,"heat_index":58.6,"pressure":29.89,"precip_rate":0,"precip_total":0,"humidity":76,"wind_dir":264},{"station":"KCAMALIB62","date":"2022-01-31 15:59:00","temperature":58.3,"wind_speed":3.4,"wind_gust":3.4,"dew_point":51.1,"wind_chill":58.3,"heat_index":58.3,"pressure":29.9,"precip_rate":0,"precip_total":0,"humidity":77,"wind_dir":259},{"station":"KCAMALIB62","date":"2022-01-31 16:04:00","temperature":57.6,"wind_speed":2.2,"wind_gust":3.4,"dew_point":50.8,"wind_chill":57.6,"heat_index":57.6,"pressure":29.89,"precip_rate":0,"precip_total":0,"humidity":78,"wind_dir":265},{"station":"KCAMALIB62","date":"2022-01-31 16:09:00","temperature":57.6,"wind_speed":3.8,"wind_gust":4.5,"dew_point":50.4,"wind_chill":57.6,"heat_index":57.6,"pressure":29.89,"precip_rate":0,"precip_total":0,"humidity":77,"wind_dir":254},{"station":"KCAMALIB62","date":"2022-01-31 16:14:00","temperature":57.2,"wind_speed":2.2,"wind_gust":3.4,"dew_point":50.1,"wind_chill":57.2,"heat_index":57.2,"pressure":29.89,"precip_rate":0,"precip_total":0,"humidity":77,"wind_dir":283},{"station":"KCAMALIB62","date":"2022-01-31 16:19:00","temperature":57.2,"wind_speed":2.5,"wind_gust":3.4,"dew_point":50.1,"wind_chill":57.2,"heat_index":57.2,"pressure":29.9,"precip_rate":0,"precip_total":0,"humidity":77,"wind_dir":296},{"station":"KCAMALIB62","date":"2022-01-31 16:24:00","temperature":57.2,"wind_speed":2.7,"wind_gust":3.4,"dew_point":50.4,"wind_chill":57.2,"heat_index":57.2,"pressure":29.9,"precip_rate":0,"precip_total":0,"humidity":78,"wind_dir":292},{"station":"KCAMALIB62","date":"2022-01-31 16:29:00","temperature":57.4,"wind_speed":0.9,"wind_gust":1.1,"dew_point":50.2,"wind_chill":57.4,"heat_index":57.4,"pressure":29.89,"precip_rate":0,"precip_total":0,"humidity":78,"wind_dir":294},{"station":"KCAMALIB62","date":"2022-01-31 16:34:00","temperature":57.4,"wind_speed":1.1,"wind_gust":1.1,"dew_point":50.2,"wind_chill":57.4,"heat_index":57.4,"pressure":29.89,"precip_rate":0,"precip_total":0,"humidity":77,"wind_dir":301},{"station":"KCAMALIB62","date":"2022-01-31 16:39:00","temperature":57,"wind_speed":0,"wind_gust":0,"dew_point":50.2,"wind_chill":57,"heat_index":57,"pressure":29.87,"precip_rate":0,"precip_total":0,"humidity":78,"wind_dir":312},{"station":"KCAMALIB62","date":"2022-01-31 16:44:00","temperature":57,"wind_speed":0.7,"wind_gust":1.1,"dew_point":50.4,"wind_chill":57,"heat_index":57,"pressure":29.88,"precip_rate":0,"precip_total":0,"humidity":79,"wind_dir":301},{"station":"KCAMALIB62","date":"2022-01-31 16:49:00","temperature":56.8,"wind_speed":0.4,"wind_gust":1.1,"dew_point":50.4,"wind_chill":56.8,"heat_index":56.8,"pressure":29.88,"precip_rate":0,"precip_total":0,"humidity":79,"wind_dir":297},{"station":"KCAMALIB62","date":"2022-01-31 16:54:00","temperature":56.7,"wind_speed":1.3,"wind_gust":2.2,"dew_point":50.6,"wind_chill":56.7,"heat_index":56.7,"pressure":29.88,"precip_rate":0,"precip_total":0,"humidity":80,"wind_dir":299},{"station":"KCAMALIB62","date":"2022-01-31 16:59:00","temperature":56.7,"wind_speed":1.6,"wind_gust":2.2,"dew_point":50.9,"wind_chill":56.7,"heat_index":56.7,"pressure":29.88,"precip_rate":0,"precip_total":0,"humidity":81,"wind_dir":282},{"station":"KCAMALIB62","date":"2022-01-31 17:04:00","temperature":56.5,"wind_speed":1.3,"wind_gust":2.2,"dew_point":50.7,"wind_chill":56.5,"heat_index":56.5,"pressure":29.88,"precip_rate":0,"precip_total":0,"humidity":81,"wind_dir":281},{"station":"KCAMALIB62","date":"2022-01-31 17:09:00","temperature":56.3,"wind_speed":1.6,"wind_gust":2.2,"dew_point":50.9,"wind_chill":56.3,"heat_index":56.3,"pressure":29.88,"precip_rate":0,"precip_total":0,"humidity":82,"wind_dir":294},{"station":"KCAMALIB62","date":"2022-01-31 17:14:00","temperature":56.3,"wind_speed":0.9,"wind_gust":1.1,"dew_point":50.9,"wind_chill":56.3,"heat_index":56.3,"pressure":29.89,"precip_rate":0,"precip_total":0,"humidity":82,"wind_dir":297},{"station":"KCAMALIB62","date":"2022-01-31 17:19:00","temperature":56.3,"wind_speed":2.2,"wind_gust":3.4,"dew_point":50.9,"wind_chill":56.3,"heat_index":56.3,"pressure":29.89,"precip_rate":0,"precip_total":0,"humidity":82,"wind_dir":304},{"station":"KCAMALIB62","date":"2022-01-31 17:24:00","temperature":56.1,"wind_speed":0.2,"wind_gust":1.1,"dew_point":51,"wind_chill":56.1,"heat_index":56.1,"pressure":29.88,"precip_rate":0,"precip_total":0,"humidity":83,"wind_dir":246},{"station":"KCAMALIB62","date":"2022-01-31 17:29:00","temperature":55.9,"wind_speed":0.7,"wind_gust":1.1,"dew_point":50.8,"wind_chill":55.9,"heat_index":55.9,"pressure":29.87,"precip_rate":0,"precip_total":0,"humidity":83,"wind_dir":288},{"station":"KCAMALIB62","date":"2022-01-31 17:34:00","temperature":55.8,"wind_speed":0.2,"wind_gust":1.1,"dew_point":50.7,"wind_chill":55.8,"heat_index":55.8,"pressure":29.88,"precip_rate":0,"precip_total":0,"humidity":83,"wind_dir":299},{"station":"KCAMALIB62","date":"2022-01-31 17:39:00","temperature":55.8,"wind_speed":0.7,"wind_gust":1.1,"dew_point":50.7,"wind_chill":55.8,"heat_index":55.8,"pressure":29.88,"precip_rate":0,"precip_total":0,"humidity":83,"wind_dir":298},{"station":"KCAMALIB62","date":"2022-01-31 17:44:00","temperature":55.8,"wind_speed":0.2,"wind_gust":1.1,"dew_point":50.7,"wind_chill":55.8,"heat_index":55.8,"pressure":29.88,"precip_rate":0,"precip_total":0,"humidity":83,"wind_dir":287},{"station":"KCAMALIB62","date":"2022-01-31 17:49:00","temperature":55.6,"wind_speed":0,"wind_gust":0,"dew_point":50.8,"wind_chill":55.6,"heat_index":55.6,"pressure":29.88,"precip_rate":0,"precip_total":0,"humidity":84,"wind_dir":299},{"station":"KCAMALIB62","date":"2022-01-31 17:54:00","temperature":55.4,"wind_speed":0,"wind_gust":0,"dew_point":50.6,"wind_chill":55.4,"heat_index":55.4,"pressure":29.88,"precip_rate":0,"precip_total":0,"humidity":84,"wind_dir":299},{"station":"KCAMALIB62","date":"2022-01-31 17:59:00","temperature":55.4,"wind_speed":0.4,"wind_gust":1.1,"dew_point":50.6,"wind_chill":55.4,"heat_index":55.4,"pressure":29.88,"precip_rate":0,"precip_total":0,"humidity":84,"wind_dir":283},{"station":"KCAMALIB62","date":"2022-01-31 18:04:00","temperature":55.4,"wind_speed":0.7,"wind_gust":1.1,"dew_point":50.6,"wind_chill":55.4,"heat_index":55.4,"pressure":29.89,"precip_rate":0,"precip_total":0,"humidity":84,"wind_dir":290},{"station":"KCAMALIB62","date":"2022-01-31 18:09:00","temperature":55.4,"wind_speed":0.9,"wind_gust":1.1,"dew_point":51,"wind_chill":55.4,"heat_index":55.4,"pressure":29.88,"precip_rate":0,"precip_total":0,"humidity":85,"wind_dir":291},{"station":"KCAMALIB62","date":"2022-01-31 18:14:00","temperature":55.2,"wind_speed":0.4,"wind_gust":1.1,"dew_point":50.8,"wind_chill":55.2,"heat_index":55.2,"pressure":29.88,"precip_rate":0,"precip_total":0,"humidity":85,"wind_dir":289},{"station":"KCAMALIB62","date":"2022-01-31 18:19:00","temperature":55.2,"wind_speed":0,"wind_gust":0,"dew_point":50.8,"wind_chill":55.2,"heat_index":55.2,"pressure":29.88,"precip_rate":0,"precip_total":0,"humidity":85,"wind_dir":289},{"station":"KCAMALIB62","date":"2022-01-31 18:24:00","temperature":55,"wind_speed":0,"wind_gust":0,"dew_point":50.6,"wind_chill":55,"heat_index":55,"pressure":29.89,"precip_rate":0,"precip_total":0,"humidity":85,"wind_dir":304},{"station":"KCAMALIB62","date":"2022-01-31 18:29:00","temperature":55,"wind_speed":0,"wind_gust":0,"dew_point":50.6,"wind_chill":55,"heat_index":55,"pressure":29.88,"precip_rate":0,"precip_total":0,"humidity":85,"wind_dir":313},{"station":"KCAMALIB62","date":"2022-01-31 18:34:00","temperature":55,"wind_speed":0,"wind_gust":0,"dew_point":50.6,"wind_chill":55,"heat_index":55,"pressure":29.88,"precip_rate":0,"precip_total":0,"humidity":85,"wind_dir":300},{"station":"KCAMALIB62","date":"2022-01-31 18:39:00","temperature":54.9,"wind_speed":0,"wind_gust":0,"dew_point":50.5,"wind_chill":54.9,"heat_index":54.9,"pressure":29.89,"precip_rate":0,"precip_total":0,"humidity":85,"wind_dir":298},{"station":"KCAMALIB62","date":"2022-01-31 18:44:00","temperature":54.9,"wind_speed":0,"wind_gust":0,"dew_point":50.5,"wind_chill":54.9,"heat_index":54.9,"pressure":29.88,"precip_rate":0,"precip_total":0,"humidity":85,"wind_dir":308},{"station":"KCAMALIB62","date":"2022-01-31 18:49:00","temperature":54.9,"wind_speed":0,"wind_gust":0,"dew_point":50.8,"wind_chill":54.9,"heat_index":54.9,"pressure":29.88,"precip_rate":0,"precip_total":0,"humidity":86,"wind_dir":316},{"station":"KCAMALIB62","date":"2022-01-31 18:54:00","temperature":54.9,"wind_speed":0,"wind_gust":0,"dew_point":50.8,"wind_chill":54.9,"heat_index":54.9,"pressure":29.88,"precip_rate":0,"precip_total":0,"humidity":86,"wind_dir":315},{"station":"KCAMALIB62","date":"2022-01-31 18:59:00","temperature":54.5,"wind_speed":0,"wind_gust":0,"dew_point":50.4,"wind_chill":54.5,"heat_index":54.5,"pressure":29.89,"precip_rate":0,"precip_total":0,"humidity":86,"wind_dir":315},{"station":"KCAMALIB62","date":"2022-01-31 19:03:00","temperature":54.5,"wind_speed":0,"wind_gust":0,"dew_point":50.4,"wind_chill":54.5,"heat_index":54.5,"pressure":29.89,"precip_rate":0,"precip_total":0,"humidity":86,"wind_dir":315},{"station":"KCAMALIB62","date":"2022-01-31 19:09:00","temperature":54.3,"wind_speed":0,"wind_gust":0,"dew_point":50.2,"wind_chill":54.3,"heat_index":54.3,"pressure":29.89,"precip_rate":0,"precip_total":0,"humidity":86,"wind_dir":315},{"station":"KCAMALIB62","date":"2022-01-31 19:14:00","temperature":54.3,"wind_speed":0,"wind_gust":0,"dew_point":50.2,"wind_chill":54.3,"heat_index":54.3,"pressure":29.89,"precip_rate":0,"precip_total":0,"humidity":86,"wind_dir":315},{"station":"KCAMALIB62","date":"2022-01-31 19:19:00","temperature":54.3,"wind_speed":0,"wind_gust":0,"dew_point":50.2,"wind_chill":54.3,"heat_index":54.3,"pressure":29.88,"precip_rate":0,"precip_total":0,"humidity":86,"wind_dir":315},{"station":"KCAMALIB62","date":"2022-01-31 19:24:00","temperature":54.1,"wind_speed":0,"wind_gust":0,"dew_point":49.7,"wind_chill":54.1,"heat_index":54.1,"pressure":29.89,"precip_rate":0,"precip_total":0,"humidity":85,"wind_dir":315},{"station":"KCAMALIB62","date":"2022-01-31 19:29:00","temperature":54.1,"wind_speed":0,"wind_gust":0,"dew_point":50,"wind_chill":54.1,"heat_index":54.1,"pressure":29.88,"precip_rate":0,"precip_total":0,"humidity":86,"wind_dir":315},{"station":"KCAMALIB62","date":"2022-01-31 19:34:00","temperature":54.1,"wind_speed":0,"wind_gust":0,"dew_point":50,"wind_chill":54.1,"heat_index":54.1,"pressure":29.88,"precip_rate":0,"precip_total":0,"humidity":86,"wind_dir":317},{"station":"KCAMALIB62","date":"2022-01-31 19:38:00","temperature":54,"wind_speed":0,"wind_gust":0,"dew_point":49.9,"wind_chill":54,"heat_index":54,"pressure":29.88,"precip_rate":0,"precip_total":0,"humidity":86,"wind_dir":316},{"station":"KCAMALIB62","date":"2022-01-31 19:44:00","temperature":54,"wind_speed":0,"wind_gust":0,"dew_point":49.9,"wind_chill":54,"heat_index":54,"pressure":29.88,"precip_rate":0,"precip_total":0,"humidity":86,"wind_dir":316},{"station":"KCAMALIB62","date":"2022-01-31 19:49:00","temperature":54,"wind_speed":0.2,"wind_gust":1.1,"dew_point":49.9,"wind_chill":54,"heat_index":54,"pressure":29.87,"precip_rate":0,"precip_total":0,"humidity":86,"wind_dir":315},{"station":"KCAMALIB62","date":"2022-01-31 19:54:00","temperature":54,"wind_speed":0.9,"wind_gust":1.1,"dew_point":49.9,"wind_chill":54,"heat_index":54,"pressure":29.87,"precip_rate":0,"precip_total":0,"humidity":86,"wind_dir":313},{"station":"KCAMALIB62","date":"2022-01-31 19:59:00","temperature":53.6,"wind_speed":0,"wind_gust":0,"dew_point":48.9,"wind_chill":53.6,"heat_index":53.6,"pressure":29.87,"precip_rate":0,"precip_total":0,"humidity":84,"wind_dir":324},{"station":"KCAMALIB62","date":"2022-01-31 20:04:00","temperature":53.4,"wind_speed":0.2,"wind_gust":1.1,"dew_point":48.7,"wind_chill":53.4,"heat_index":53.4,"pressure":29.86,"precip_rate":0,"precip_total":0,"humidity":84,"wind_dir":313},{"station":"KCAMALIB62","date":"2022-01-31 20:09:00","temperature":53.8,"wind_speed":0.9,"wind_gust":1.1,"dew_point":49.2,"wind_chill":53.8,"heat_index":53.8,"pressure":29.86,"precip_rate":0,"precip_total":0,"humidity":85,"wind_dir":325},{"station":"KCAMALIB62","date":"2022-01-31 20:14:00","temperature":53.8,"wind_speed":0.2,"wind_gust":1.1,"dew_point":49.4,"wind_chill":53.8,"heat_index":53.8,"pressure":29.87,"precip_rate":0,"precip_total":0,"humidity":85,"wind_dir":333},{"station":"KCAMALIB62","date":"2022-01-31 20:19:00","temperature":53.8,"wind_speed":0,"wind_gust":0,"dew_point":49.4,"wind_chill":53.8,"heat_index":53.8,"pressure":29.87,"precip_rate":0,"precip_total":0,"humidity":85,"wind_dir":314},{"station":"KCAMALIB62","date":"2022-01-31 20:24:00","temperature":53.2,"wind_speed":0.2,"wind_gust":1.1,"dew_point":48.8,"wind_chill":53.2,"heat_index":53.2,"pressure":29.87,"precip_rate":0,"precip_total":0,"humidity":85,"wind_dir":293},{"station":"KCAMALIB62","date":"2022-01-31 20:29:00","temperature":53.2,"wind_speed":0,"wind_gust":0,"dew_point":48.8,"wind_chill":53.2,"heat_index":53.2,"pressure":29.87,"precip_rate":0,"precip_total":0,"humidity":85,"wind_dir":306},{"station":"KCAMALIB62","date":"2022-01-31 20:34:00","temperature":53.2,"wind_speed":0,"wind_gust":0,"dew_point":48.8,"wind_chill":53.2,"heat_index":53.2,"pressure":29.88,"precip_rate":0,"precip_total":0,"humidity":85,"wind_dir":306},{"station":"KCAMALIB62","date":"2022-01-31 20:39:00","temperature":52.9,"wind_speed":0,"wind_gust":0,"dew_point":48.2,"wind_chill":52.9,"heat_index":52.9,"pressure":29.88,"precip_rate":0,"precip_total":0,"humidity":84,"wind_dir":306},{"station":"KCAMALIB62","date":"2022-01-31 20:44:00","temperature":52.7,"wind_speed":0.2,"wind_gust":1.1,"dew_point":48.3,"wind_chill":52.7,"heat_index":52.7,"pressure":29.87,"precip_rate":0,"precip_total":0,"humidity":85,"wind_dir":320},{"station":"KCAMALIB62","date":"2022-01-31 20:49:00","temperature":52.5,"wind_speed":0,"wind_gust":0,"dew_point":48.1,"wind_chill":52.5,"heat_index":52.5,"pressure":29.88,"precip_rate":0,"precip_total":0,"humidity":85,"wind_dir":317},{"station":"KCAMALIB62","date":"2022-01-31 20:54:00","temperature":52.3,"wind_speed":0,"wind_gust":0,"dew_point":48.2,"wind_chill":52.3,"heat_index":52.3,"pressure":29.87,"precip_rate":0,"precip_total":0,"humidity":86,"wind_dir":316},{"station":"KCAMALIB62","date":"2022-01-31 20:59:00","temperature":52.3,"wind_speed":0,"wind_gust":0,"dew_point":48.4,"wind_chill":52.3,"heat_index":52.3,"pressure":29.88,"precip_rate":0,"precip_total":0,"humidity":87,"wind_dir":316},{"station":"KCAMALIB62","date":"2022-01-31 21:04:00","temperature":52.3,"wind_speed":0.4,"wind_gust":1.1,"dew_point":48.9,"wind_chill":52.3,"heat_index":52.3,"pressure":29.87,"precip_rate":0,"precip_total":0,"humidity":88,"wind_dir":322},{"station":"KCAMALIB62","date":"2022-01-31 21:09:00","temperature":52.3,"wind_speed":0,"wind_gust":0,"dew_point":48.9,"wind_chill":52.3,"heat_index":52.3,"pressure":29.87,"precip_rate":0,"precip_total":0,"humidity":88,"wind_dir":314},{"station":"KCAMALIB62","date":"2022-01-31 21:14:00","temperature":52.3,"wind_speed":0,"wind_gust":0,"dew_point":48.9,"wind_chill":52.3,"heat_index":52.3,"pressure":29.87,"precip_rate":0,"precip_total":0,"humidity":88,"wind_dir":307},{"station":"KCAMALIB62","date":"2022-01-31 21:19:00","temperature":52.3,"wind_speed":0.2,"wind_gust":1.1,"dew_point":48.5,"wind_chill":52.3,"heat_index":52.3,"pressure":29.87,"precip_rate":0,"precip_total":0,"humidity":87,"wind_dir":317},{"station":"KCAMALIB62","date":"2022-01-31 21:24:00","temperature":52.5,"wind_speed":0,"wind_gust":0,"dew_point":48.4,"wind_chill":52.5,"heat_index":52.5,"pressure":29.86,"precip_rate":0,"precip_total":0,"humidity":86,"wind_dir":317},{"station":"KCAMALIB62","date":"2022-01-31 21:29:00","temperature":52.5,"wind_speed":0,"wind_gust":0,"dew_point":48.4,"wind_chill":52.5,"heat_index":52.5,"pressure":29.86,"precip_rate":0,"precip_total":0,"humidity":86,"wind_dir":317},{"station":"KCAMALIB62","date":"2022-01-31 21:34:00","temperature":52.5,"wind_speed":0,"wind_gust":0,"dew_point":48.4,"wind_chill":52.5,"heat_index":52.5,"pressure":29.86,"precip_rate":0,"precip_total":0,"humidity":86,"wind_dir":317},{"station":"KCAMALIB62","date":"2022-01-31 21:38:00","temperature":52.3,"wind_speed":0,"wind_gust":0,"dew_point":48.2,"wind_chill":52.3,"heat_index":52.3,"pressure":29.86,"precip_rate":0,"precip_total":0,"humidity":86,"wind_dir":317},{"station":"KCAMALIB62","date":"2022-01-31 21:44:00","temperature":52.2,"wind_speed":0.9,"wind_gust":1.1,"dew_point":47.9,"wind_chill":52.2,"heat_index":52.2,"pressure":29.86,"precip_rate":0,"precip_total":0,"humidity":86,"wind_dir":345},{"station":"KCAMALIB62","date":"2022-01-31 21:49:00","temperature":52.2,"wind_speed":0.2,"wind_gust":1.1,"dew_point":47.8,"wind_chill":52.2,"heat_index":52.2,"pressure":29.86,"precip_rate":0,"precip_total":0,"humidity":85,"wind_dir":301},{"station":"KCAMALIB62","date":"2022-01-31 21:54:00","temperature":52.3,"wind_speed":0,"wind_gust":0,"dew_point":48.2,"wind_chill":52.3,"heat_index":52.3,"pressure":29.86,"precip_rate":0,"precip_total":0,"humidity":86,"wind_dir":313},{"station":"KCAMALIB62","date":"2022-01-31 21:59:00","temperature":52.3,"wind_speed":0,"wind_gust":0,"dew_point":47.9,"wind_chill":52.3,"heat_index":52.3,"pressure":29.86,"precip_rate":0,"precip_total":0,"humidity":85,"wind_dir":307},{"station":"KCAMALIB62","date":"2022-01-31 22:04:00","temperature":52.2,"wind_speed":0,"wind_gust":0,"dew_point":47.9,"wind_chill":52.2,"heat_index":52.2,"pressure":29.86,"precip_rate":0,"precip_total":0,"humidity":86,"wind_dir":307},{"station":"KCAMALIB62","date":"2022-01-31 22:09:00","temperature":52,"wind_speed":0,"wind_gust":0,"dew_point":47.9,"wind_chill":52,"heat_index":52,"pressure":29.86,"precip_rate":0,"precip_total":0,"humidity":86,"wind_dir":312},{"station":"KCAMALIB62","date":"2022-01-31 22:14:00","temperature":51.8,"wind_speed":0.2,"wind_gust":1.1,"dew_point":47.7,"wind_chill":51.8,"heat_index":51.8,"pressure":29.86,"precip_rate":0,"precip_total":0,"humidity":86,"wind_dir":312},{"station":"KCAMALIB62","date":"2022-01-31 22:19:00","temperature":51.6,"wind_speed":0,"wind_gust":0,"dew_point":47.2,"wind_chill":51.6,"heat_index":51.6,"pressure":29.85,"precip_rate":0,"precip_total":0,"humidity":85,"wind_dir":312},{"station":"KCAMALIB62","date":"2022-01-31 22:24:00","temperature":51.8,"wind_speed":0,"wind_gust":0,"dew_point":47.1,"wind_chill":51.8,"heat_index":51.8,"pressure":29.85,"precip_rate":0,"precip_total":0,"humidity":85,"wind_dir":312},{"station":"KCAMALIB62","date":"2022-01-31 22:29:00","temperature":52,"wind_speed":0,"wind_gust":0,"dew_point":47,"wind_chill":52,"heat_index":52,"pressure":29.85,"precip_rate":0,"precip_total":0,"humidity":83,"wind_dir":312},{"station":"KCAMALIB62","date":"2022-01-31 22:34:00","temperature":52,"wind_speed":0,"wind_gust":0,"dew_point":46.7,"wind_chill":52,"heat_index":52,"pressure":29.86,"precip_rate":0,"precip_total":0,"humidity":82,"wind_dir":312},{"station":"KCAMALIB62","date":"2022-01-31 22:39:00","temperature":51.8,"wind_speed":0,"wind_gust":0,"dew_point":46.5,"wind_chill":51.8,"heat_index":51.8,"pressure":29.85,"precip_rate":0,"precip_total":0,"humidity":82,"wind_dir":317},{"station":"KCAMALIB62","date":"2022-01-31 22:44:00","temperature":51.4,"wind_speed":0,"wind_gust":0,"dew_point":46.1,"wind_chill":51.4,"heat_index":51.4,"pressure":29.85,"precip_rate":0,"precip_total":0,"humidity":82,"wind_dir":317},{"station":"KCAMALIB62","date":"2022-01-31 22:49:00","temperature":51.3,"wind_speed":0,"wind_gust":0,"dew_point":45.7,"wind_chill":51.3,"heat_index":51.3,"pressure":29.85,"precip_rate":0,"precip_total":0,"humidity":81,"wind_dir":317},{"station":"KCAMALIB62","date":"2022-01-31 22:54:00","temperature":51.4,"wind_speed":0,"wind_gust":0,"dew_point":45.4,"wind_chill":51.4,"heat_index":51.4,"pressure":29.85,"precip_rate":0,"precip_total":0,"humidity":80,"wind_dir":317},{"station":"KCAMALIB62","date":"2022-01-31 22:59:00","temperature":51.6,"wind_speed":0,"wind_gust":0,"dew_point":45.6,"wind_chill":51.6,"heat_index":51.6,"pressure":29.85,"precip_rate":0,"precip_total":0,"humidity":80,"wind_dir":317},{"station":"KCAMALIB62","date":"2022-01-31 23:04:00","temperature":51.4,"wind_speed":0,"wind_gust":0,"dew_point":45.4,"wind_chill":51.4,"heat_index":51.4,"pressure":29.85,"precip_rate":0,"precip_total":0,"humidity":80,"wind_dir":317},{"station":"KCAMALIB62","date":"2022-01-31 23:09:00","temperature":51.1,"wind_speed":0.2,"wind_gust":1.1,"dew_point":45.3,"wind_chill":51.1,"heat_index":51.1,"pressure":29.85,"precip_rate":0,"precip_total":0,"humidity":81,"wind_dir":317},{"station":"KCAMALIB62","date":"2022-01-31 23:14:00","temperature":50.9,"wind_speed":0,"wind_gust":0,"dew_point":45,"wind_chill":50.9,"heat_index":50.9,"pressure":29.86,"precip_rate":0,"precip_total":0,"humidity":80,"wind_dir":317},{"station":"KCAMALIB62","date":"2022-01-31 23:19:00","temperature":50.7,"wind_speed":0,"wind_gust":0,"dew_point":44.8,"wind_chill":50.7,"heat_index":50.7,"pressure":29.85,"precip_rate":0,"precip_total":0,"humidity":80,"wind_dir":318},{"station":"KCAMALIB62","date":"2022-01-31 23:24:00","temperature":50.9,"wind_speed":0,"wind_gust":0,"dew_point":45,"wind_chill":50.9,"heat_index":50.9,"pressure":29.86,"precip_rate":0,"precip_total":0,"humidity":80,"wind_dir":317},{"station":"KCAMALIB62","date":"2022-01-31 23:29:00","temperature":50.9,"wind_speed":0,"wind_gust":0,"dew_point":45,"wind_chill":50.9,"heat_index":50.9,"pressure":29.85,"precip_rate":0,"precip_total":0,"humidity":80,"wind_dir":317},{"station":"KCAMALIB62","date":"2022-01-31 23:34:00","temperature":51.1,"wind_speed":0.2,"wind_gust":1.1,"dew_point":44.6,"wind_chill":51.1,"heat_index":51.1,"pressure":29.86,"precip_rate":0,"precip_total":0,"humidity":79,"wind_dir":322},{"station":"KCAMALIB62","date":"2022-01-31 23:39:00","temperature":51.1,"wind_speed":0.7,"wind_gust":1.1,"dew_point":44.5,"wind_chill":51.1,"heat_index":51.1,"pressure":29.86,"precip_rate":0,"precip_total":0,"humidity":78,"wind_dir":310},{"station":"KCAMALIB62","date":"2022-01-31 23:44:00","temperature":51.3,"wind_speed":0,"wind_gust":0,"dew_point":45,"wind_chill":51.3,"heat_index":51.3,"pressure":29.86,"precip_rate":0,"precip_total":0,"humidity":79,"wind_dir":313},{"station":"KCAMALIB62","date":"2022-01-31 23:49:00","temperature":51.4,"wind_speed":0.9,"wind_gust":1.1,"dew_point":45.1,"wind_chill":51.4,"heat_index":51.4,"pressure":29.86,"precip_rate":0,"precip_total":0,"humidity":79,"wind_dir":318},{"station":"KCAMALIB62","date":"2022-01-31 23:54:00","temperature":51.3,"wind_speed":0,"wind_gust":0,"dew_point":45.3,"wind_chill":51.3,"heat_index":51.3,"pressure":29.86,"precip_rate":0,"precip_total":0,"humidity":80,"wind_dir":320},{"station":"KCAMALIB62","date":"2022-01-31 23:59:00","temperature":51.1,"wind_speed":0,"wind_gust":0,"dew_point":45.1,"wind_chill":51.1,"heat_index":51.1,"pressure":29.85,"precip_rate":0,"precip_total":0,"humidity":80,"wind_dir":302}]