[{"station":"KCAMALIB62","date":"2022-12-29 00:04:00","temperature":54.5,"wind_speed":0.2,"wind_gust":1.1,"dew_point":51.6,"wind_chill":54.5,"heat_index":54.5,"pressure":29.84,"precip_rate":0,"precip_total":0,"humidity":90,"wind_dir":307},{"station":"KCAMALIB62","date":"2022-12-29 00:09:00","temperature":54.3,"wind_speed":0.7,"wind_gust":1.1,"dew_point":51.4,"wind_chill":54.3,"heat_index":54.3,"pressure":29.83,"precip_rate":0,"precip_total":0,"humidity":90,"wind_dir":313},{"station":"KCAMALIB62","date":"2022-12-29 00:14:00","temperature":54.7,"wind_speed":1.8,"wind_gust":2.2,"dew_point":51.8,"wind_chill":54.7,"heat_index":54.7,"pressure":29.82,"precip_rate":0,"precip_total":0,"humidity":90,"wind_dir":328},{"station":"KCAMALIB62","date":"2022-12-29 00:19:00","temperature":55,"wind_speed":1.6,"wind_gust":2.2,"dew_point":51.7,"wind_chill":55,"heat_index":55,"pressure":29.82,"precip_rate":0,"precip_total":0,"humidity":89,"wind_dir":337},{"station":"KCAMALIB62","date":"2022-12-29 00:24:00","temperature":55.4,"wind_speed":0.9,"wind_gust":1.1,"dew_point":51.6,"wind_chill":55.4,"heat_index":55.4,"pressure":29.82,"precip_rate":0,"precip_total":0,"humidity":88,"wind_dir":314},{"station":"KCAMALIB62","date":"2022-12-29 00:29:00","temperature":55.4,"wind_speed":0.2,"wind_gust":1.1,"dew_point":51.3,"wind_chill":55.4,"heat_index":55.4,"pressure":29.82,"precip_rate":0,"precip_total":0,"humidity":86,"wind_dir":304},{"station":"KCAMALIB62","date":"2022-12-29 00:34:00","temperature":55.6,"wind_speed":0,"wind_gust":0,"dew_point":51.5,"wind_chill":55.6,"heat_index":55.6,"pressure":29.83,"precip_rate":0,"precip_total":0,"humidity":86,"wind_dir":305},{"station":"KCAMALIB62","date":"2022-12-29 00:39:00","temperature":55.6,"wind_speed":0,"wind_gust":0,"dew_point":51.5,"wind_chill":55.6,"heat_index":55.6,"pressure":29.82,"precip_rate":0,"precip_total":0,"humidity":86,"wind_dir":312},{"station":"KCAMALIB62","date":"2022-12-29 00:44:00","temperature":55.4,"wind_speed":0.2,"wind_gust":1.1,"dew_point":51.3,"wind_chill":55.4,"heat_index":55.4,"pressure":29.82,"precip_rate":0,"precip_total":0,"humidity":86,"wind_dir":306},{"station":"KCAMALIB62","date":"2022-12-29 00:49:00","temperature":55.6,"wind_speed":0,"wind_gust":0,"dew_point":51.5,"wind_chill":55.6,"heat_index":55.6,"pressure":29.82,"precip_rate":0,"precip_total":0,"humidity":86,"wind_dir":308},{"station":"KCAMALIB62","date":"2022-12-29 00:54:00","temperature":55.8,"wind_speed":0.9,"wind_gust":1.1,"dew_point":51.7,"wind_chill":55.8,"heat_index":55.8,"pressure":29.81,"precip_rate":0,"precip_total":0,"humidity":86,"wind_dir":343},{"station":"KCAMALIB62","date":"2022-12-29 00:59:00","temperature":55.8,"wind_speed":1.1,"wind_gust":2.2,"dew_point":51.7,"wind_chill":55.8,"heat_index":55.8,"pressure":29.81,"precip_rate":0,"precip_total":0,"humidity":86,"wind_dir":34},{"station":"KCAMALIB62","date":"2022-12-29 01:04:00","temperature":55.6,"wind_speed":0.2,"wind_gust":1.1,"dew_point":51.5,"wind_chill":55.6,"heat_index":55.6,"pressure":29.8,"precip_rate":0,"precip_total":0,"humidity":86,"wind_dir":310},{"station":"KCAMALIB62","date":"2022-12-29 01:09:00","temperature":55.6,"wind_speed":0.7,"wind_gust":1.1,"dew_point":51.5,"wind_chill":55.6,"heat_index":55.6,"pressure":29.81,"precip_rate":0,"precip_total":0,"humidity":86,"wind_dir":300},{"station":"KCAMALIB62","date":"2022-12-29 01:14:00","temperature":55.6,"wind_speed":0.7,"wind_gust":1.1,"dew_point":51.5,"wind_chill":55.6,"heat_index":55.6,"pressure":29.8,"precip_rate":0,"precip_total":0,"humidity":86,"wind_dir":323},{"station":"KCAMALIB62","date":"2022-12-29 01:19:00","temperature":55.6,"wind_speed":0.9,"wind_gust":1.1,"dew_point":51.5,"wind_chill":55.6,"heat_index":55.6,"pressure":29.8,"precip_rate":0,"precip_total":0,"humidity":86,"wind_dir":12},{"station":"KCAMALIB62","date":"2022-12-29 01:24:00","temperature":55.6,"wind_speed":0.2,"wind_gust":1.1,"dew_point":51.5,"wind_chill":55.6,"heat_index":55.6,"pressure":29.81,"precip_rate":0,"precip_total":0,"humidity":86,"wind_dir":281},{"station":"KCAMALIB62","date":"2022-12-29 01:29:00","temperature":55.6,"wind_speed":0,"wind_gust":0,"dew_point":51.5,"wind_chill":55.6,"heat_index":55.6,"pressure":29.81,"precip_rate":0,"precip_total":0,"humidity":86,"wind_dir":306},{"station":"KCAMALIB62","date":"2022-12-29 01:34:00","temperature":55.6,"wind_speed":0,"wind_gust":0,"dew_point":51.8,"wind_chill":55.6,"heat_index":55.6,"pressure":29.81,"precip_rate":0,"precip_total":0,"humidity":87,"wind_dir":306},{"station":"KCAMALIB62","date":"2022-12-29 01:39:00","temperature":55.6,"wind_speed":0,"wind_gust":0,"dew_point":51.8,"wind_chill":55.6,"heat_index":55.6,"pressure":29.81,"precip_rate":0,"precip_total":0,"humidity":87,"wind_dir":312},{"station":"KCAMALIB62","date":"2022-12-29 01:44:00","temperature":55.6,"wind_speed":0.2,"wind_gust":1.1,"dew_point":51.8,"wind_chill":55.6,"heat_index":55.6,"pressure":29.81,"precip_rate":0,"precip_total":0,"humidity":87,"wind_dir":323},{"station":"KCAMALIB62","date":"2022-12-29 01:49:00","temperature":55.4,"wind_speed":0.4,"wind_gust":1.1,"dew_point":51.9,"wind_chill":55.4,"heat_index":55.4,"pressure":29.81,"precip_rate":0,"precip_total":0,"humidity":88,"wind_dir":320},{"station":"KCAMALIB62","date":"2022-12-29 01:54:00","temperature":55.6,"wind_speed":1.3,"wind_gust":2.2,"dew_point":52.1,"wind_chill":55.6,"heat_index":55.6,"pressure":29.81,"precip_rate":0,"precip_total":0,"humidity":88,"wind_dir":353},{"station":"KCAMALIB62","date":"2022-12-29 01:59:00","temperature":55.8,"wind_speed":0,"wind_gust":0,"dew_point":52.1,"wind_chill":55.8,"heat_index":55.8,"pressure":29.81,"precip_rate":0,"precip_total":0,"humidity":88,"wind_dir":304},{"station":"KCAMALIB62","date":"2022-12-29 02:04:00","temperature":55.8,"wind_speed":0.7,"wind_gust":1.1,"dew_point":52,"wind_chill":55.8,"heat_index":55.8,"pressure":29.81,"precip_rate":0,"precip_total":0,"humidity":87,"wind_dir":329},{"station":"KCAMALIB62","date":"2022-12-29 02:09:00","temperature":55.8,"wind_speed":1.1,"wind_gust":2.2,"dew_point":52,"wind_chill":55.8,"heat_index":55.8,"pressure":29.81,"precip_rate":0,"precip_total":0,"humidity":87,"wind_dir":349},{"station":"KCAMALIB62","date":"2022-12-29 02:14:00","temperature":55.8,"wind_speed":0.2,"wind_gust":1.1,"dew_point":51.7,"wind_chill":55.8,"heat_index":55.8,"pressure":29.81,"precip_rate":0,"precip_total":0,"humidity":86,"wind_dir":326},{"station":"KCAMALIB62","date":"2022-12-29 02:19:00","temperature":55.8,"wind_speed":0.4,"wind_gust":1.1,"dew_point":51.7,"wind_chill":55.8,"heat_index":55.8,"pressure":29.81,"precip_rate":0,"precip_total":0,"humidity":86,"wind_dir":330},{"station":"KCAMALIB62","date":"2022-12-29 02:24:00","temperature":55.8,"wind_speed":2.2,"wind_gust":2.2,"dew_point":51.7,"wind_chill":55.8,"heat_index":55.8,"pressure":29.81,"precip_rate":0,"precip_total":0,"humidity":86,"wind_dir":343},{"station":"KCAMALIB62","date":"2022-12-29 02:29:00","temperature":55.8,"wind_speed":1.1,"wind_gust":2.2,"dew_point":51.7,"wind_chill":55.8,"heat_index":55.8,"pressure":29.8,"precip_rate":0,"precip_total":0,"humidity":86,"wind_dir":309},{"station":"KCAMALIB62","date":"2022-12-29 02:34:00","temperature":55.8,"wind_speed":1.8,"wind_gust":2.2,"dew_point":51.7,"wind_chill":55.8,"heat_index":55.8,"pressure":29.8,"precip_rate":0,"precip_total":0,"humidity":86,"wind_dir":212},{"station":"KCAMALIB62","date":"2022-12-29 02:39:00","temperature":55.9,"wind_speed":2.2,"wind_gust":3.4,"dew_point":51.8,"wind_chill":55.9,"heat_index":55.9,"pressure":29.8,"precip_rate":0,"precip_total":0,"humidity":86,"wind_dir":54},{"station":"KCAMALIB62","date":"2022-12-29 02:44:00","temperature":55.9,"wind_speed":0.2,"wind_gust":1.1,"dew_point":51.8,"wind_chill":55.9,"heat_index":55.9,"pressure":29.8,"precip_rate":0,"precip_total":0,"humidity":86,"wind_dir":301},{"station":"KCAMALIB62","date":"2022-12-29 02:49:00","temperature":55.8,"wind_speed":1.8,"wind_gust":2.2,"dew_point":51.7,"wind_chill":55.8,"heat_index":55.8,"pressure":29.78,"precip_rate":0,"precip_total":0,"humidity":86,"wind_dir":344},{"station":"KCAMALIB62","date":"2022-12-29 02:54:00","temperature":55.9,"wind_speed":2.5,"wind_gust":3.4,"dew_point":51.8,"wind_chill":55.9,"heat_index":55.9,"pressure":29.8,"precip_rate":0,"precip_total":0,"humidity":86,"wind_dir":316},{"station":"KCAMALIB62","date":"2022-12-29 02:59:00","temperature":55.9,"wind_speed":0.9,"wind_gust":1.1,"dew_point":51.8,"wind_chill":55.9,"heat_index":55.9,"pressure":29.81,"precip_rate":0,"precip_total":0,"humidity":86,"wind_dir":303},{"station":"KCAMALIB62","date":"2022-12-29 03:04:00","temperature":55.9,"wind_speed":1.3,"wind_gust":2.2,"dew_point":51.8,"wind_chill":55.9,"heat_index":55.9,"pressure":29.82,"precip_rate":0,"precip_total":0,"humidity":86,"wind_dir":320},{"station":"KCAMALIB62","date":"2022-12-29 03:09:00","temperature":56.1,"wind_speed":1.8,"wind_gust":2.2,"dew_point":52,"wind_chill":56.1,"heat_index":56.1,"pressure":29.82,"precip_rate":0,"precip_total":0,"humidity":86,"wind_dir":6},{"station":"KCAMALIB62","date":"2022-12-29 03:14:00","temperature":56.1,"wind_speed":0.9,"wind_gust":1.1,"dew_point":52,"wind_chill":56.1,"heat_index":56.1,"pressure":29.83,"precip_rate":0,"precip_total":0,"humidity":86,"wind_dir":312},{"station":"KCAMALIB62","date":"2022-12-29 03:19:00","temperature":56.1,"wind_speed":1.1,"wind_gust":1.1,"dew_point":52,"wind_chill":56.1,"heat_index":56.1,"pressure":29.82,"precip_rate":0,"precip_total":0,"humidity":86,"wind_dir":330},{"station":"KCAMALIB62","date":"2022-12-29 03:24:00","temperature":56.1,"wind_speed":0.2,"wind_gust":1.1,"dew_point":52,"wind_chill":56.1,"heat_index":56.1,"pressure":29.82,"precip_rate":0,"precip_total":0,"humidity":86,"wind_dir":310},{"station":"KCAMALIB62","date":"2022-12-29 03:29:00","temperature":56.1,"wind_speed":1.1,"wind_gust":2.2,"dew_point":52.3,"wind_chill":56.1,"heat_index":56.1,"pressure":29.82,"precip_rate":0,"precip_total":0,"humidity":87,"wind_dir":338},{"station":"KCAMALIB62","date":"2022-12-29 03:34:00","temperature":56.1,"wind_speed":1.6,"wind_gust":2.2,"dew_point":52.3,"wind_chill":56.1,"heat_index":56.1,"pressure":29.81,"precip_rate":0,"precip_total":0,"humidity":87,"wind_dir":346},{"station":"KCAMALIB62","date":"2022-12-29 03:39:00","temperature":55.9,"wind_speed":0.9,"wind_gust":2.2,"dew_point":52.1,"wind_chill":55.9,"heat_index":55.9,"pressure":29.81,"precip_rate":0,"precip_total":0,"humidity":87,"wind_dir":329},{"station":"KCAMALIB62","date":"2022-12-29 03:44:00","temperature":55.9,"wind_speed":2.2,"wind_gust":3.4,"dew_point":52.1,"wind_chill":55.9,"heat_index":55.9,"pressure":29.81,"precip_rate":0,"precip_total":0,"humidity":87,"wind_dir":51},{"station":"KCAMALIB62","date":"2022-12-29 03:49:00","temperature":55.9,"wind_speed":0.9,"wind_gust":1.1,"dew_point":52.1,"wind_chill":55.9,"heat_index":55.9,"pressure":29.81,"precip_rate":0,"precip_total":0,"humidity":87,"wind_dir":346},{"station":"KCAMALIB62","date":"2022-12-29 03:54:00","temperature":55.9,"wind_speed":1.6,"wind_gust":2.2,"dew_point":52.4,"wind_chill":55.9,"heat_index":55.9,"pressure":29.79,"precip_rate":0,"precip_total":0,"humidity":88,"wind_dir":330},{"station":"KCAMALIB62","date":"2022-12-29 03:59:00","temperature":55.8,"wind_speed":1.8,"wind_gust":2.2,"dew_point":52.3,"wind_chill":55.8,"heat_index":55.8,"pressure":29.81,"precip_rate":0,"precip_total":0,"humidity":88,"wind_dir":22},{"station":"KCAMALIB62","date":"2022-12-29 04:04:00","temperature":55.8,"wind_speed":1.8,"wind_gust":2.2,"dew_point":52.3,"wind_chill":55.8,"heat_index":55.8,"pressure":29.82,"precip_rate":0,"precip_total":0,"humidity":88,"wind_dir":2},{"station":"KCAMALIB62","date":"2022-12-29 04:09:00","temperature":55.8,"wind_speed":1.1,"wind_gust":2.2,"dew_point":52.3,"wind_chill":55.8,"heat_index":55.8,"pressure":29.83,"precip_rate":0,"precip_total":0,"humidity":88,"wind_dir":35},{"station":"KCAMALIB62","date":"2022-12-29 04:14:00","temperature":55.9,"wind_speed":1.3,"wind_gust":2.2,"dew_point":52.4,"wind_chill":55.9,"heat_index":55.9,"pressure":29.83,"precip_rate":0,"precip_total":0,"humidity":88,"wind_dir":326},{"station":"KCAMALIB62","date":"2022-12-29 04:19:00","temperature":55.8,"wind_speed":1.3,"wind_gust":2.2,"dew_point":52.6,"wind_chill":55.8,"heat_index":55.8,"pressure":29.83,"precip_rate":0,"precip_total":0,"humidity":89,"wind_dir":266},{"station":"KCAMALIB62","date":"2022-12-29 04:24:00","temperature":55.8,"wind_speed":3.1,"wind_gust":4.5,"dew_point":52.6,"wind_chill":55.8,"heat_index":55.8,"pressure":29.83,"precip_rate":0,"precip_total":0,"humidity":89,"wind_dir":322},{"station":"KCAMALIB62","date":"2022-12-29 04:29:00","temperature":55.8,"wind_speed":2,"wind_gust":2.2,"dew_point":52.6,"wind_chill":55.8,"heat_index":55.8,"pressure":29.82,"precip_rate":0,"precip_total":0,"humidity":89,"wind_dir":48},{"station":"KCAMALIB62","date":"2022-12-29 04:34:00","temperature":55.8,"wind_speed":1.3,"wind_gust":2.2,"dew_point":52.6,"wind_chill":55.8,"heat_index":55.8,"pressure":29.81,"precip_rate":0,"precip_total":0,"humidity":89,"wind_dir":38},{"station":"KCAMALIB62","date":"2022-12-29 04:39:00","temperature":55.8,"wind_speed":1.3,"wind_gust":2.2,"dew_point":52.6,"wind_chill":55.8,"heat_index":55.8,"pressure":29.82,"precip_rate":0,"precip_total":0,"humidity":89,"wind_dir":17},{"station":"KCAMALIB62","date":"2022-12-29 04:44:00","temperature":55.6,"wind_speed":2.7,"wind_gust":4.5,"dew_point":52.4,"wind_chill":55.6,"heat_index":55.6,"pressure":29.82,"precip_rate":0,"precip_total":0,"humidity":89,"wind_dir":334},{"station":"KCAMALIB62","date":"2022-12-29 04:49:00","temperature":55.6,"wind_speed":1.6,"wind_gust":4.5,"dew_point":52.4,"wind_chill":55.6,"heat_index":55.6,"pressure":29.82,"precip_rate":0,"precip_total":0,"humidity":89,"wind_dir":27},{"station":"KCAMALIB62","date":"2022-12-29 04:54:00","temperature":55.6,"wind_speed":0.7,"wind_gust":1.1,"dew_point":52.1,"wind_chill":55.6,"heat_index":55.6,"pressure":29.82,"precip_rate":0,"precip_total":0,"humidity":88,"wind_dir":340},{"station":"KCAMALIB62","date":"2022-12-29 04:59:00","temperature":55.6,"wind_speed":2,"wind_gust":2.2,"dew_point":52.1,"wind_chill":55.6,"heat_index":55.6,"pressure":29.83,"precip_rate":0,"precip_total":0,"humidity":88,"wind_dir":22},{"station":"KCAMALIB62","date":"2022-12-29 05:04:00","temperature":55.6,"wind_speed":0.7,"wind_gust":1.1,"dew_point":52.1,"wind_chill":55.6,"heat_index":55.6,"pressure":29.83,"precip_rate":0,"precip_total":0,"humidity":88,"wind_dir":315},{"station":"KCAMALIB62","date":"2022-12-29 05:09:00","temperature":55.6,"wind_speed":2,"wind_gust":2.2,"dew_point":52.1,"wind_chill":55.6,"heat_index":55.6,"pressure":29.83,"precip_rate":0,"precip_total":0,"humidity":88,"wind_dir":335},{"station":"KCAMALIB62","date":"2022-12-29 05:14:00","temperature":55.6,"wind_speed":0,"wind_gust":0,"dew_point":52.1,"wind_chill":55.6,"heat_index":55.6,"pressure":29.84,"precip_rate":0,"precip_total":0,"humidity":88,"wind_dir":306},{"station":"KCAMALIB62","date":"2022-12-29 05:19:00","temperature":55.6,"wind_speed":0.7,"wind_gust":1.1,"dew_point":52.1,"wind_chill":55.6,"heat_index":55.6,"pressure":29.83,"precip_rate":0,"precip_total":0,"humidity":88,"wind_dir":309},{"station":"KCAMALIB62","date":"2022-12-29 05:24:00","temperature":55.6,"wind_speed":0,"wind_gust":0,"dew_point":51.8,"wind_chill":55.6,"heat_index":55.6,"pressure":29.84,"precip_rate":0,"precip_total":0,"humidity":87,"wind_dir":311},{"station":"KCAMALIB62","date":"2022-12-29 05:29:00","temperature":55.6,"wind_speed":1.1,"wind_gust":2.2,"dew_point":51.8,"wind_chill":55.6,"heat_index":55.6,"pressure":29.85,"precip_rate":0,"precip_total":0,"humidity":87,"wind_dir":328},{"station":"KCAMALIB62","date":"2022-12-29 05:34:00","temperature":55.6,"wind_speed":0,"wind_gust":0,"dew_point":51.8,"wind_chill":55.6,"heat_index":55.6,"pressure":29.85,"precip_rate":0,"precip_total":0,"humidity":87,"wind_dir":305},{"station":"KCAMALIB62","date":"2022-12-29 05:39:00","temperature":55.6,"wind_speed":0,"wind_gust":0,"dew_point":51.8,"wind_chill":55.6,"heat_index":55.6,"pressure":29.86,"precip_rate":0,"precip_total":0,"humidity":87,"wind_dir":303},{"station":"KCAMALIB62","date":"2022-12-29 05:44:00","temperature":55.4,"wind_speed":0.2,"wind_gust":1.1,"dew_point":51.6,"wind_chill":55.4,"heat_index":55.4,"pressure":29.85,"precip_rate":0,"precip_total":0,"humidity":87,"wind_dir":305},{"station":"KCAMALIB62","date":"2022-12-29 05:49:00","temperature":55.6,"wind_speed":0.9,"wind_gust":1.1,"dew_point":51.8,"wind_chill":55.6,"heat_index":55.6,"pressure":29.84,"precip_rate":0,"precip_total":0,"humidity":87,"wind_dir":352},{"station":"KCAMALIB62","date":"2022-12-29 05:54:00","temperature":55.6,"wind_speed":0.2,"wind_gust":1.1,"dew_point":51.8,"wind_chill":55.6,"heat_index":55.6,"pressure":29.84,"precip_rate":0,"precip_total":0,"humidity":87,"wind_dir":310},{"station":"KCAMALIB62","date":"2022-12-29 05:59:00","temperature":55.4,"wind_speed":0.2,"wind_gust":1.1,"dew_point":51.6,"wind_chill":55.4,"heat_index":55.4,"pressure":29.84,"precip_rate":0,"precip_total":0,"humidity":87,"wind_dir":305},{"station":"KCAMALIB62","date":"2022-12-29 06:04:00","temperature":55.4,"wind_speed":0.9,"wind_gust":2.2,"dew_point":51.6,"wind_chill":55.4,"heat_index":55.4,"pressure":29.83,"precip_rate":0,"precip_total":0,"humidity":87,"wind_dir":11},{"station":"KCAMALIB62","date":"2022-12-29 06:09:00","temperature":55.4,"wind_speed":0.7,"wind_gust":1.1,"dew_point":51.6,"wind_chill":55.4,"heat_index":55.4,"pressure":29.84,"precip_rate":0,"precip_total":0,"humidity":87,"wind_dir":310},{"station":"KCAMALIB62","date":"2022-12-29 06:14:00","temperature":55.4,"wind_speed":0.7,"wind_gust":1.1,"dew_point":51.6,"wind_chill":55.4,"heat_index":55.4,"pressure":29.84,"precip_rate":0,"precip_total":0,"humidity":87,"wind_dir":12},{"station":"KCAMALIB62","date":"2022-12-29 06:19:00","temperature":55.4,"wind_speed":0.7,"wind_gust":1.1,"dew_point":51.9,"wind_chill":55.4,"heat_index":55.4,"pressure":29.84,"precip_rate":0,"precip_total":0,"humidity":88,"wind_dir":337},{"station":"KCAMALIB62","date":"2022-12-29 06:24:00","temperature":55.2,"wind_speed":0.4,"wind_gust":1.1,"dew_point":51.7,"wind_chill":55.2,"heat_index":55.2,"pressure":29.85,"precip_rate":0,"precip_total":0,"humidity":88,"wind_dir":357},{"station":"KCAMALIB62","date":"2022-12-29 06:29:00","temperature":55.2,"wind_speed":0,"wind_gust":0,"dew_point":51.7,"wind_chill":55.2,"heat_index":55.2,"pressure":29.85,"precip_rate":0,"precip_total":0,"humidity":88,"wind_dir":306},{"station":"KCAMALIB62","date":"2022-12-29 06:34:00","temperature":55.2,"wind_speed":0,"wind_gust":0,"dew_point":51.7,"wind_chill":55.2,"heat_index":55.2,"pressure":29.85,"precip_rate":0,"precip_total":0,"humidity":88,"wind_dir":313},{"station":"KCAMALIB62","date":"2022-12-29 06:39:00","temperature":55.2,"wind_speed":0,"wind_gust":0,"dew_point":51.7,"wind_chill":55.2,"heat_index":55.2,"pressure":29.86,"precip_rate":0,"precip_total":0,"humidity":88,"wind_dir":305},{"station":"KCAMALIB62","date":"2022-12-29 06:44:00","temperature":55.2,"wind_speed":0,"wind_gust":0,"dew_point":51.7,"wind_chill":55.2,"heat_index":55.2,"pressure":29.86,"precip_rate":0,"precip_total":0,"humidity":88,"wind_dir":312},{"station":"KCAMALIB62","date":"2022-12-29 06:49:00","temperature":55,"wind_speed":0,"wind_gust":0,"dew_point":51.8,"wind_chill":55,"heat_index":55,"pressure":29.86,"precip_rate":0,"precip_total":0,"humidity":89,"wind_dir":310},{"station":"KCAMALIB62","date":"2022-12-29 06:54:00","temperature":55,"wind_speed":0,"wind_gust":0,"dew_point":51.8,"wind_chill":55,"heat_index":55,"pressure":29.85,"precip_rate":0,"precip_total":0,"humidity":89,"wind_dir":315},{"station":"KCAMALIB62","date":"2022-12-29 06:59:00","temperature":55,"wind_speed":1.3,"wind_gust":2.2,"dew_point":51.8,"wind_chill":55,"heat_index":55,"pressure":29.86,"precip_rate":0,"precip_total":0,"humidity":89,"wind_dir":327},{"station":"KCAMALIB62","date":"2022-12-29 07:04:00","temperature":55,"wind_speed":0.2,"wind_gust":1.1,"dew_point":51.8,"wind_chill":55,"heat_index":55,"pressure":29.86,"precip_rate":0,"precip_total":0,"humidity":89,"wind_dir":313},{"station":"KCAMALIB62","date":"2022-12-29 07:09:00","temperature":55,"wind_speed":0.2,"wind_gust":1.1,"dew_point":51.8,"wind_chill":55,"heat_index":55,"pressure":29.86,"precip_rate":0,"precip_total":0,"humidity":89,"wind_dir":313},{"station":"KCAMALIB62","date":"2022-12-29 07:14:00","temperature":55.2,"wind_speed":0,"wind_gust":0,"dew_point":51.7,"wind_chill":55.2,"heat_index":55.2,"pressure":29.86,"precip_rate":0,"precip_total":0,"humidity":88,"wind_dir":332},{"station":"KCAMALIB62","date":"2022-12-29 07:19:00","temperature":55.2,"wind_speed":0.9,"wind_gust":1.1,"dew_point":51.7,"wind_chill":55.2,"heat_index":55.2,"pressure":29.86,"precip_rate":0,"precip_total":0,"humidity":88,"wind_dir":304},{"station":"KCAMALIB62","date":"2022-12-29 07:24:00","temperature":55.2,"wind_speed":0,"wind_gust":0,"dew_point":51.7,"wind_chill":55.2,"heat_index":55.2,"pressure":29.86,"precip_rate":0,"precip_total":0,"humidity":88,"wind_dir":306},{"station":"KCAMALIB62","date":"2022-12-29 07:29:00","temperature":55.2,"wind_speed":0.7,"wind_gust":1.1,"dew_point":51.7,"wind_chill":55.2,"heat_index":55.2,"pressure":29.87,"precip_rate":0,"precip_total":0,"humidity":88,"wind_dir":352},{"station":"KCAMALIB62","date":"2022-12-29 07:34:00","temperature":55.2,"wind_speed":0.2,"wind_gust":1.1,"dew_point":51.7,"wind_chill":55.2,"heat_index":55.2,"pressure":29.87,"precip_rate":0,"precip_total":0,"humidity":88,"wind_dir":319},{"station":"KCAMALIB62","date":"2022-12-29 07:39:00","temperature":55.4,"wind_speed":0.2,"wind_gust":1.1,"dew_point":51.7,"wind_chill":55.4,"heat_index":55.4,"pressure":29.87,"precip_rate":0,"precip_total":0,"humidity":88,"wind_dir":321},{"station":"KCAMALIB62","date":"2022-12-29 07:44:00","temperature":55.6,"wind_speed":0,"wind_gust":0,"dew_point":51.8,"wind_chill":55.6,"heat_index":55.6,"pressure":29.87,"precip_rate":0,"precip_total":0,"humidity":87,"wind_dir":355},{"station":"KCAMALIB62","date":"2022-12-29 07:49:00","temperature":55.6,"wind_speed":0.9,"wind_gust":1.1,"dew_point":51.8,"wind_chill":55.6,"heat_index":55.6,"pressure":29.86,"precip_rate":0,"precip_total":0,"humidity":87,"wind_dir":341},{"station":"KCAMALIB62","date":"2022-12-29 07:54:00","temperature":55.8,"wind_speed":2.2,"wind_gust":2.2,"dew_point":51.7,"wind_chill":55.8,"heat_index":55.8,"pressure":29.86,"precip_rate":0,"precip_total":0,"humidity":86,"wind_dir":339},{"station":"KCAMALIB62","date":"2022-12-29 07:59:00","temperature":55.9,"wind_speed":1.6,"wind_gust":2.2,"dew_point":51.5,"wind_chill":55.9,"heat_index":55.9,"pressure":29.87,"precip_rate":0,"precip_total":0,"humidity":85,"wind_dir":359},{"station":"KCAMALIB62","date":"2022-12-29 08:04:00","temperature":56.1,"wind_speed":0.4,"wind_gust":1.1,"dew_point":51.3,"wind_chill":56.1,"heat_index":56.1,"pressure":29.87,"precip_rate":0,"precip_total":0,"humidity":84,"wind_dir":316},{"station":"KCAMALIB62","date":"2022-12-29 08:09:00","temperature":56.1,"wind_speed":0.9,"wind_gust":1.1,"dew_point":51.3,"wind_chill":56.1,"heat_index":56.1,"pressure":29.86,"precip_rate":0,"precip_total":0,"humidity":84,"wind_dir":315},{"station":"KCAMALIB62","date":"2022-12-29 08:14:00","temperature":56.3,"wind_speed":1.1,"wind_gust":1.1,"dew_point":51.2,"wind_chill":56.3,"heat_index":56.3,"pressure":29.87,"precip_rate":0,"precip_total":0,"humidity":83,"wind_dir":345},{"station":"KCAMALIB62","date":"2022-12-29 08:19:00","temperature":56.5,"wind_speed":0,"wind_gust":0,"dew_point":51.2,"wind_chill":56.5,"heat_index":56.5,"pressure":29.87,"precip_rate":0,"precip_total":0,"humidity":83,"wind_dir":304},{"station":"KCAMALIB62","date":"2022-12-29 08:24:00","temperature":56.7,"wind_speed":0.9,"wind_gust":1.1,"dew_point":51.1,"wind_chill":56.7,"heat_index":56.7,"pressure":29.88,"precip_rate":0,"precip_total":0,"humidity":82,"wind_dir":318},{"station":"KCAMALIB62","date":"2022-12-29 08:29:00","temperature":56.8,"wind_speed":0,"wind_gust":0,"dew_point":51,"wind_chill":56.8,"heat_index":56.8,"pressure":29.87,"precip_rate":0,"precip_total":0,"humidity":81,"wind_dir":302},{"station":"KCAMALIB62","date":"2022-12-29 08:34:00","temperature":57,"wind_speed":0,"wind_gust":0,"dew_point":51,"wind_chill":57,"heat_index":57,"pressure":29.88,"precip_rate":0,"precip_total":0,"humidity":81,"wind_dir":305},{"station":"KCAMALIB62","date":"2022-12-29 08:39:00","temperature":57.4,"wind_speed":1.1,"wind_gust":1.1,"dew_point":51.3,"wind_chill":57.4,"heat_index":57.4,"pressure":29.87,"precip_rate":0,"precip_total":0,"humidity":80,"wind_dir":317},{"station":"KCAMALIB62","date":"2022-12-29 08:44:00","temperature":57.6,"wind_speed":1.1,"wind_gust":1.1,"dew_point":51.5,"wind_chill":57.6,"heat_index":57.6,"pressure":29.87,"precip_rate":0,"precip_total":0,"humidity":80,"wind_dir":6},{"station":"KCAMALIB62","date":"2022-12-29 08:49:00","temperature":57.6,"wind_speed":0.4,"wind_gust":1.1,"dew_point":51.5,"wind_chill":57.6,"heat_index":57.6,"pressure":29.89,"precip_rate":0,"precip_total":0,"humidity":80,"wind_dir":348},{"station":"KCAMALIB62","date":"2022-12-29 08:54:00","temperature":57.4,"wind_speed":0.9,"wind_gust":1.1,"dew_point":51.3,"wind_chill":57.4,"heat_index":57.4,"pressure":29.89,"precip_rate":0,"precip_total":0,"humidity":80,"wind_dir":305},{"station":"KCAMALIB62","date":"2022-12-29 08:59:00","temperature":57.4,"wind_speed":1.8,"wind_gust":2.2,"dew_point":51.4,"wind_chill":57.4,"heat_index":57.4,"pressure":29.89,"precip_rate":0,"precip_total":0,"humidity":81,"wind_dir":332},{"station":"KCAMALIB62","date":"2022-12-29 09:04:00","temperature":57.2,"wind_speed":0.4,"wind_gust":1.1,"dew_point":51.4,"wind_chill":57.2,"heat_index":57.2,"pressure":29.89,"precip_rate":0,"precip_total":0,"humidity":81,"wind_dir":317},{"station":"KCAMALIB62","date":"2022-12-29 09:09:00","temperature":57.2,"wind_speed":0.2,"wind_gust":1.1,"dew_point":51.4,"wind_chill":57.2,"heat_index":57.2,"pressure":29.89,"precip_rate":0,"precip_total":0,"humidity":81,"wind_dir":250},{"station":"KCAMALIB62","date":"2022-12-29 09:14:00","temperature":57.4,"wind_speed":0.9,"wind_gust":1.1,"dew_point":51.6,"wind_chill":57.4,"heat_index":57.4,"pressure":29.89,"precip_rate":0,"precip_total":0,"humidity":81,"wind_dir":322},{"station":"KCAMALIB62","date":"2022-12-29 09:19:00","temperature":57.6,"wind_speed":0.9,"wind_gust":1.1,"dew_point":51.8,"wind_chill":57.6,"heat_index":57.6,"pressure":29.89,"precip_rate":0,"precip_total":0,"humidity":81,"wind_dir":321},{"station":"KCAMALIB62","date":"2022-12-29 09:24:00","temperature":57.6,"wind_speed":1.3,"wind_gust":2.2,"dew_point":51.8,"wind_chill":57.6,"heat_index":57.6,"pressure":29.88,"precip_rate":0,"precip_total":0,"humidity":81,"wind_dir":337},{"station":"KCAMALIB62","date":"2022-12-29 09:29:00","temperature":57.9,"wind_speed":0.4,"wind_gust":1.1,"dew_point":52.1,"wind_chill":57.9,"heat_index":57.9,"pressure":29.88,"precip_rate":0,"precip_total":0,"humidity":81,"wind_dir":352},{"station":"KCAMALIB62","date":"2022-12-29 09:34:00","temperature":57.9,"wind_speed":2.5,"wind_gust":3.4,"dew_point":52.1,"wind_chill":57.9,"heat_index":57.9,"pressure":29.88,"precip_rate":0,"precip_total":0,"humidity":81,"wind_dir":357},{"station":"KCAMALIB62","date":"2022-12-29 09:39:00","temperature":57.6,"wind_speed":2.5,"wind_gust":3.4,"dew_point":51.8,"wind_chill":57.6,"heat_index":57.6,"pressure":29.88,"precip_rate":0,"precip_total":0,"humidity":81,"wind_dir":59},{"station":"KCAMALIB62","date":"2022-12-29 09:44:00","temperature":57.6,"wind_speed":2.9,"wind_gust":4.5,"dew_point":51.9,"wind_chill":57.6,"heat_index":57.6,"pressure":29.89,"precip_rate":0,"precip_total":0,"humidity":82,"wind_dir":342},{"station":"KCAMALIB62","date":"2022-12-29 09:49:00","temperature":57.6,"wind_speed":1.8,"wind_gust":3.4,"dew_point":52.1,"wind_chill":57.6,"heat_index":57.6,"pressure":29.89,"precip_rate":0,"precip_total":0,"humidity":82,"wind_dir":352},{"station":"KCAMALIB62","date":"2022-12-29 09:54:00","temperature":57.6,"wind_speed":2,"wind_gust":3.4,"dew_point":52.5,"wind_chill":57.6,"heat_index":57.6,"pressure":29.89,"precip_rate":0,"precip_total":0,"humidity":83,"wind_dir":24},{"station":"KCAMALIB62","date":"2022-12-29 09:59:00","temperature":57.4,"wind_speed":1.6,"wind_gust":2.2,"dew_point":52.3,"wind_chill":57.4,"heat_index":57.4,"pressure":29.9,"precip_rate":0,"precip_total":0,"humidity":83,"wind_dir":89},{"station":"KCAMALIB62","date":"2022-12-29 10:04:00","temperature":57.6,"wind_speed":1.8,"wind_gust":3.4,"dew_point":52.5,"wind_chill":57.6,"heat_index":57.6,"pressure":29.89,"precip_rate":0,"precip_total":0,"humidity":83,"wind_dir":28},{"station":"KCAMALIB62","date":"2022-12-29 10:09:00","temperature":57.7,"wind_speed":2,"wind_gust":3.4,"dew_point":52.9,"wind_chill":57.7,"heat_index":57.7,"pressure":29.89,"precip_rate":0,"precip_total":0,"humidity":84,"wind_dir":279},{"station":"KCAMALIB62","date":"2022-12-29 10:14:00","temperature":57.7,"wind_speed":0.9,"wind_gust":1.1,"dew_point":52.9,"wind_chill":57.7,"heat_index":57.7,"pressure":29.9,"precip_rate":0,"precip_total":0,"humidity":84,"wind_dir":315},{"station":"KCAMALIB62","date":"2022-12-29 10:18:00","temperature":57.7,"wind_speed":2,"wind_gust":2.2,"dew_point":52.9,"wind_chill":57.7,"heat_index":57.7,"pressure":29.9,"precip_rate":0,"precip_total":0,"humidity":84,"wind_dir":11},{"station":"KCAMALIB62","date":"2022-12-29 10:24:00","temperature":57.7,"wind_speed":1.3,"wind_gust":2.2,"dew_point":52.9,"wind_chill":57.7,"heat_index":57.7,"pressure":29.9,"precip_rate":0,"precip_total":0,"humidity":84,"wind_dir":29},{"station":"KCAMALIB62","date":"2022-12-29 10:29:00","temperature":57.6,"wind_speed":1.6,"wind_gust":2.2,"dew_point":53.1,"wind_chill":57.6,"heat_index":57.6,"pressure":29.9,"precip_rate":0,"precip_total":0,"humidity":85,"wind_dir":7},{"station":"KCAMALIB62","date":"2022-12-29 10:34:00","temperature":57.7,"wind_speed":1.8,"wind_gust":3.4,"dew_point":53.2,"wind_chill":57.7,"heat_index":57.7,"pressure":29.89,"precip_rate":0,"precip_total":0,"humidity":85,"wind_dir":309},{"station":"KCAMALIB62","date":"2022-12-29 10:39:00","temperature":57.7,"wind_speed":1.3,"wind_gust":2.2,"dew_point":53.2,"wind_chill":57.7,"heat_index":57.7,"pressure":29.89,"precip_rate":0,"precip_total":0,"humidity":85,"wind_dir":298},{"station":"KCAMALIB62","date":"2022-12-29 10:44:00","temperature":57.6,"wind_speed":2,"wind_gust":3.4,"dew_point":53.4,"wind_chill":57.6,"heat_index":57.6,"pressure":29.9,"precip_rate":0,"precip_total":0,"humidity":86,"wind_dir":334},{"station":"KCAMALIB62","date":"2022-12-29 10:49:00","temperature":57.6,"wind_speed":1.6,"wind_gust":2.2,"dew_point":53.4,"wind_chill":57.6,"heat_index":57.6,"pressure":29.9,"precip_rate":0,"precip_total":0,"humidity":86,"wind_dir":12},{"station":"KCAMALIB62","date":"2022-12-29 10:54:00","temperature":57.4,"wind_speed":1.3,"wind_gust":2.2,"dew_point":52.9,"wind_chill":57.4,"heat_index":57.4,"pressure":29.89,"precip_rate":0,"precip_total":0,"humidity":85,"wind_dir":35},{"station":"KCAMALIB62","date":"2022-12-29 10:59:00","temperature":57.4,"wind_speed":3.4,"wind_gust":4.5,"dew_point":52.9,"wind_chill":57.4,"heat_index":57.4,"pressure":29.89,"precip_rate":0,"precip_total":0,"humidity":85,"wind_dir":74},{"station":"KCAMALIB62","date":"2022-12-29 11:04:00","temperature":57.4,"wind_speed":2.2,"wind_gust":3.4,"dew_point":52.9,"wind_chill":57.4,"heat_index":57.4,"pressure":29.89,"precip_rate":0,"precip_total":0,"humidity":85,"wind_dir":53},{"station":"KCAMALIB62","date":"2022-12-29 11:09:00","temperature":57.6,"wind_speed":1.8,"wind_gust":3.4,"dew_point":53.1,"wind_chill":57.6,"heat_index":57.6,"pressure":29.88,"precip_rate":0,"precip_total":0,"humidity":85,"wind_dir":358},{"station":"KCAMALIB62","date":"2022-12-29 11:14:00","temperature":57.6,"wind_speed":0.9,"wind_gust":2.2,"dew_point":53.4,"wind_chill":57.6,"heat_index":57.6,"pressure":29.89,"precip_rate":0,"precip_total":0,"humidity":86,"wind_dir":337},{"station":"KCAMALIB62","date":"2022-12-29 11:19:00","temperature":57.6,"wind_speed":2.2,"wind_gust":2.2,"dew_point":53.4,"wind_chill":57.6,"heat_index":57.6,"pressure":29.89,"precip_rate":0,"precip_total":0,"humidity":86,"wind_dir":356},{"station":"KCAMALIB62","date":"2022-12-29 11:24:00","temperature":57.4,"wind_speed":1.3,"wind_gust":2.2,"dew_point":53.2,"wind_chill":57.4,"heat_index":57.4,"pressure":29.88,"precip_rate":0,"precip_total":0,"humidity":86,"wind_dir":15},{"station":"KCAMALIB62","date":"2022-12-29 11:29:00","temperature":57.4,"wind_speed":1.1,"wind_gust":1.1,"dew_point":53.2,"wind_chill":57.4,"heat_index":57.4,"pressure":29.88,"precip_rate":0,"precip_total":0,"humidity":86,"wind_dir":52},{"station":"KCAMALIB62","date":"2022-12-29 11:34:00","temperature":57.4,"wind_speed":1.3,"wind_gust":2.2,"dew_point":53.2,"wind_chill":57.4,"heat_index":57.4,"pressure":29.88,"precip_rate":0,"precip_total":0,"humidity":86,"wind_dir":6},{"station":"KCAMALIB62","date":"2022-12-29 11:39:00","temperature":57.6,"wind_speed":1.6,"wind_gust":2.2,"dew_point":53.4,"wind_chill":57.6,"heat_index":57.6,"pressure":29.88,"precip_rate":0,"precip_total":0,"humidity":86,"wind_dir":348},{"station":"KCAMALIB62","date":"2022-12-29 11:44:00","temperature":57.6,"wind_speed":1.1,"wind_gust":2.2,"dew_point":53.4,"wind_chill":57.6,"heat_index":57.6,"pressure":29.88,"precip_rate":0,"precip_total":0,"humidity":86,"wind_dir":49},{"station":"KCAMALIB62","date":"2022-12-29 11:49:00","temperature":57.6,"wind_speed":1.1,"wind_gust":2.2,"dew_point":53.4,"wind_chill":57.6,"heat_index":57.6,"pressure":29.88,"precip_rate":0,"precip_total":0,"humidity":86,"wind_dir":338},{"station":"KCAMALIB62","date":"2022-12-29 11:54:00","temperature":57.7,"wind_speed":1.1,"wind_gust":2.2,"dew_point":53.5,"wind_chill":57.7,"heat_index":57.7,"pressure":29.88,"precip_rate":0,"precip_total":0,"humidity":86,"wind_dir":308},{"station":"KCAMALIB62","date":"2022-12-29 11:59:00","temperature":57.7,"wind_speed":1.6,"wind_gust":2.2,"dew_point":53.5,"wind_chill":57.7,"heat_index":57.7,"pressure":29.87,"precip_rate":0,"precip_total":0,"humidity":86,"wind_dir":24},{"station":"KCAMALIB62","date":"2022-12-29 12:04:00","temperature":57.6,"wind_speed":0.9,"wind_gust":1.1,"dew_point":53.4,"wind_chill":57.6,"heat_index":57.6,"pressure":29.87,"precip_rate":0,"precip_total":0,"humidity":86,"wind_dir":44},{"station":"KCAMALIB62","date":"2022-12-29 12:09:00","temperature":57.7,"wind_speed":0.9,"wind_gust":1.1,"dew_point":53.5,"wind_chill":57.7,"heat_index":57.7,"pressure":29.87,"precip_rate":0,"precip_total":0,"humidity":86,"wind_dir":294},{"station":"KCAMALIB62","date":"2022-12-29 12:14:00","temperature":57.7,"wind_speed":1.3,"wind_gust":2.2,"dew_point":53.5,"wind_chill":57.7,"heat_index":57.7,"pressure":29.86,"precip_rate":0,"precip_total":0,"humidity":86,"wind_dir":340},{"station":"KCAMALIB62","date":"2022-12-29 12:19:00","temperature":57.7,"wind_speed":1.8,"wind_gust":2.2,"dew_point":53.5,"wind_chill":57.7,"heat_index":57.7,"pressure":29.86,"precip_rate":0,"precip_total":0,"humidity":86,"wind_dir":340},{"station":"KCAMALIB62","date":"2022-12-29 12:24:00","temperature":57.9,"wind_speed":1.1,"wind_gust":1.1,"dew_point":53.7,"wind_chill":57.9,"heat_index":57.9,"pressure":29.87,"precip_rate":0,"precip_total":0,"humidity":86,"wind_dir":337},{"station":"KCAMALIB62","date":"2022-12-29 12:29:00","temperature":57.9,"wind_speed":1.3,"wind_gust":2.2,"dew_point":53.7,"wind_chill":57.9,"heat_index":57.9,"pressure":29.86,"precip_rate":0,"precip_total":0,"humidity":86,"wind_dir":10},{"station":"KCAMALIB62","date":"2022-12-29 12:34:00","temperature":57.9,"wind_speed":0.9,"wind_gust":1.1,"dew_point":53.7,"wind_chill":57.9,"heat_index":57.9,"pressure":29.86,"precip_rate":0,"precip_total":0,"humidity":86,"wind_dir":336},{"station":"KCAMALIB62","date":"2022-12-29 12:39:00","temperature":57.7,"wind_speed":1.1,"wind_gust":2.2,"dew_point":53.2,"wind_chill":57.7,"heat_index":57.7,"pressure":29.86,"precip_rate":0,"precip_total":0,"humidity":85,"wind_dir":18},{"station":"KCAMALIB62","date":"2022-12-29 12:44:00","temperature":57.6,"wind_speed":1.1,"wind_gust":1.1,"dew_point":52.8,"wind_chill":57.6,"heat_index":57.6,"pressure":29.86,"precip_rate":0,"precip_total":0,"humidity":84,"wind_dir":304},{"station":"KCAMALIB62","date":"2022-12-29 12:49:00","temperature":58.1,"wind_speed":0.2,"wind_gust":1.1,"dew_point":53.6,"wind_chill":58.1,"heat_index":58.1,"pressure":29.86,"precip_rate":0,"precip_total":0,"humidity":85,"wind_dir":327},{"station":"KCAMALIB62","date":"2022-12-29 12:54:00","temperature":58.1,"wind_speed":0.7,"wind_gust":1.1,"dew_point":53.3,"wind_chill":58.1,"heat_index":58.1,"pressure":29.86,"precip_rate":0,"precip_total":0,"humidity":84,"wind_dir":290},{"station":"KCAMALIB62","date":"2022-12-29 12:59:00","temperature":58.3,"wind_speed":0.7,"wind_gust":1.1,"dew_point":53.5,"wind_chill":58.3,"heat_index":58.3,"pressure":29.85,"precip_rate":0,"precip_total":0,"humidity":84,"wind_dir":314},{"station":"KCAMALIB62","date":"2022-12-29 13:04:00","temperature":58.3,"wind_speed":0.2,"wind_gust":1.1,"dew_point":53.5,"wind_chill":58.3,"heat_index":58.3,"pressure":29.86,"precip_rate":0,"precip_total":0,"humidity":84,"wind_dir":314},{"station":"KCAMALIB62","date":"2022-12-29 13:09:00","temperature":58.6,"wind_speed":0.2,"wind_gust":1.1,"dew_point":53.8,"wind_chill":58.6,"heat_index":58.6,"pressure":29.85,"precip_rate":0,"precip_total":0,"humidity":84,"wind_dir":332},{"station":"KCAMALIB62","date":"2022-12-29 13:14:00","temperature":58.6,"wind_speed":1.8,"wind_gust":2.2,"dew_point":53.5,"wind_chill":58.6,"heat_index":58.6,"pressure":29.85,"precip_rate":0,"precip_total":0,"humidity":83,"wind_dir":134},{"station":"KCAMALIB62","date":"2022-12-29 13:19:00","temperature":58.1,"wind_speed":0.9,"wind_gust":2.2,"dew_point":53,"wind_chill":58.1,"heat_index":58.1,"pressure":29.85,"precip_rate":0,"precip_total":0,"humidity":83,"wind_dir":342},{"station":"KCAMALIB62","date":"2022-12-29 13:24:00","temperature":58.1,"wind_speed":1.1,"wind_gust":1.1,"dew_point":53.3,"wind_chill":58.1,"heat_index":58.1,"pressure":29.84,"precip_rate":0,"precip_total":0,"humidity":84,"wind_dir":120},{"station":"KCAMALIB62","date":"2022-12-29 13:29:00","temperature":58.5,"wind_speed":0.7,"wind_gust":1.1,"dew_point":53.7,"wind_chill":58.5,"heat_index":58.5,"pressure":29.84,"precip_rate":0,"precip_total":0,"humidity":84,"wind_dir":316},{"station":"KCAMALIB62","date":"2022-12-29 13:34:00","temperature":58.5,"wind_speed":1.1,"wind_gust":1.1,"dew_point":53.7,"wind_chill":58.5,"heat_index":58.5,"pressure":29.84,"precip_rate":0,"precip_total":0,"humidity":84,"wind_dir":309},{"station":"KCAMALIB62","date":"2022-12-29 13:39:00","temperature":58.3,"wind_speed":0.4,"wind_gust":1.1,"dew_point":53.5,"wind_chill":58.3,"heat_index":58.3,"pressure":29.84,"precip_rate":0,"precip_total":0,"humidity":84,"wind_dir":343},{"station":"KCAMALIB62","date":"2022-12-29 13:44:00","temperature":58.1,"wind_speed":0.4,"wind_gust":1.1,"dew_point":53.3,"wind_chill":58.1,"heat_index":58.1,"pressure":29.84,"precip_rate":0,"precip_total":0,"humidity":84,"wind_dir":287},{"station":"KCAMALIB62","date":"2022-12-29 13:49:00","temperature":58.1,"wind_speed":0.7,"wind_gust":1.1,"dew_point":53.3,"wind_chill":58.1,"heat_index":58.1,"pressure":29.84,"precip_rate":0,"precip_total":0,"humidity":84,"wind_dir":313},{"station":"KCAMALIB62","date":"2022-12-29 13:54:00","temperature":58.1,"wind_speed":0.9,"wind_gust":1.1,"dew_point":53.3,"wind_chill":58.1,"heat_index":58.1,"pressure":29.84,"precip_rate":0,"precip_total":0,"humidity":84,"wind_dir":272},{"station":"KCAMALIB62","date":"2022-12-29 13:59:00","temperature":57.9,"wind_speed":1.6,"wind_gust":2.2,"dew_point":53.1,"wind_chill":57.9,"heat_index":57.9,"pressure":29.85,"precip_rate":0,"precip_total":0,"humidity":84,"wind_dir":293},{"station":"KCAMALIB62","date":"2022-12-29 14:04:00","temperature":57.9,"wind_speed":0.4,"wind_gust":1.1,"dew_point":53.1,"wind_chill":57.9,"heat_index":57.9,"pressure":29.84,"precip_rate":0,"precip_total":0,"humidity":84,"wind_dir":7},{"station":"KCAMALIB62","date":"2022-12-29 14:09:00","temperature":58.3,"wind_speed":0.9,"wind_gust":1.1,"dew_point":53.5,"wind_chill":58.3,"heat_index":58.3,"pressure":29.84,"precip_rate":0,"precip_total":0,"humidity":84,"wind_dir":149},{"station":"KCAMALIB62","date":"2022-12-29 14:14:00","temperature":58.3,"wind_speed":0.7,"wind_gust":1.1,"dew_point":53.5,"wind_chill":58.3,"heat_index":58.3,"pressure":29.84,"precip_rate":0,"precip_total":0,"humidity":84,"wind_dir":230},{"station":"KCAMALIB62","date":"2022-12-29 14:19:00","temperature":57.9,"wind_speed":0.9,"wind_gust":1.1,"dew_point":53.1,"wind_chill":57.9,"heat_index":57.9,"pressure":29.85,"precip_rate":0,"precip_total":0,"humidity":84,"wind_dir":315},{"station":"KCAMALIB62","date":"2022-12-29 14:24:00","temperature":58.1,"wind_speed":0,"wind_gust":0,"dew_point":53.6,"wind_chill":58.1,"heat_index":58.1,"pressure":29.85,"precip_rate":0,"precip_total":0,"humidity":85,"wind_dir":306},{"station":"KCAMALIB62","date":"2022-12-29 14:29:00","temperature":58.1,"wind_speed":0.4,"wind_gust":1.1,"dew_point":53.6,"wind_chill":58.1,"heat_index":58.1,"pressure":29.85,"precip_rate":0,"precip_total":0,"humidity":85,"wind_dir":325},{"station":"KCAMALIB62","date":"2022-12-29 14:34:00","temperature":57.9,"wind_speed":0.9,"wind_gust":1.1,"dew_point":53.1,"wind_chill":57.9,"heat_index":57.9,"pressure":29.86,"precip_rate":0,"precip_total":0,"humidity":84,"wind_dir":310},{"station":"KCAMALIB62","date":"2022-12-29 14:39:00","temperature":57.6,"wind_speed":0.7,"wind_gust":1.1,"dew_point":50.1,"wind_chill":57.6,"heat_index":57.6,"pressure":29.86,"precip_rate":0,"precip_total":0,"humidity":77,"wind_dir":258},{"station":"KCAMALIB62","date":"2022-12-29 14:44:00","temperature":58.1,"wind_speed":0.9,"wind_gust":1.1,"dew_point":50,"wind_chill":58.1,"heat_index":58.1,"pressure":29.86,"precip_rate":0,"precip_total":0,"humidity":75,"wind_dir":295},{"station":"KCAMALIB62","date":"2022-12-29 14:49:00","temperature":58.1,"wind_speed":0.9,"wind_gust":1.1,"dew_point":49.9,"wind_chill":58.1,"heat_index":58.1,"pressure":29.86,"precip_rate":0,"precip_total":0,"humidity":74,"wind_dir":306},{"station":"KCAMALIB62","date":"2022-12-29 14:54:00","temperature":58.1,"wind_speed":0.2,"wind_gust":1.1,"dew_point":49.9,"wind_chill":58.1,"heat_index":58.1,"pressure":29.86,"precip_rate":0,"precip_total":0,"humidity":74,"wind_dir":298},{"station":"KCAMALIB62","date":"2022-12-29 14:59:00","temperature":57.9,"wind_speed":0.9,"wind_gust":1.1,"dew_point":49.7,"wind_chill":57.9,"heat_index":57.9,"pressure":29.86,"precip_rate":0,"precip_total":0,"humidity":74,"wind_dir":295},{"station":"KCAMALIB62","date":"2022-12-29 15:04:00","temperature":58.1,"wind_speed":0.7,"wind_gust":1.1,"dew_point":49.9,"wind_chill":58.1,"heat_index":58.1,"pressure":29.86,"precip_rate":0,"precip_total":0,"humidity":74,"wind_dir":284},{"station":"KCAMALIB62","date":"2022-12-29 15:09:00","temperature":58.1,"wind_speed":0.4,"wind_gust":1.1,"dew_point":50,"wind_chill":58.1,"heat_index":58.1,"pressure":29.86,"precip_rate":0,"precip_total":0,"humidity":75,"wind_dir":293},{"station":"KCAMALIB62","date":"2022-12-29 15:14:00","temperature":58.1,"wind_speed":0.9,"wind_gust":1.1,"dew_point":50.2,"wind_chill":58.1,"heat_index":58.1,"pressure":29.87,"precip_rate":0,"precip_total":0,"humidity":75,"wind_dir":301},{"station":"KCAMALIB62","date":"2022-12-29 15:19:00","temperature":57.9,"wind_speed":0,"wind_gust":0,"dew_point":50.4,"wind_chill":57.9,"heat_index":57.9,"pressure":29.86,"precip_rate":0,"precip_total":0,"humidity":76,"wind_dir":298},{"station":"KCAMALIB62","date":"2022-12-29 15:24:00","temperature":57.9,"wind_speed":0.9,"wind_gust":1.1,"dew_point":50.4,"wind_chill":57.9,"heat_index":57.9,"pressure":29.87,"precip_rate":0,"precip_total":0,"humidity":76,"wind_dir":301},{"station":"KCAMALIB62","date":"2022-12-29 15:29:00","temperature":57.9,"wind_speed":0.2,"wind_gust":1.1,"dew_point":50.4,"wind_chill":57.9,"heat_index":57.9,"pressure":29.86,"precip_rate":0,"precip_total":0,"humidity":76,"wind_dir":307},{"station":"KCAMALIB62","date":"2022-12-29 15:34:00","temperature":57.9,"wind_speed":0.9,"wind_gust":1.1,"dew_point":50.4,"wind_chill":57.9,"heat_index":57.9,"pressure":29.87,"precip_rate":0,"precip_total":0,"humidity":76,"wind_dir":297},{"station":"KCAMALIB62","date":"2022-12-29 15:39:00","temperature":57.9,"wind_speed":0.7,"wind_gust":1.1,"dew_point":50.7,"wind_chill":57.9,"heat_index":57.9,"pressure":29.87,"precip_rate":0,"precip_total":0,"humidity":77,"wind_dir":302},{"station":"KCAMALIB62","date":"2022-12-29 15:44:00","temperature":57.9,"wind_speed":0.7,"wind_gust":1.1,"dew_point":51.1,"wind_chill":57.9,"heat_index":57.9,"pressure":29.86,"precip_rate":0,"precip_total":0,"humidity":78,"wind_dir":292},{"station":"KCAMALIB62","date":"2022-12-29 15:49:00","temperature":57.7,"wind_speed":0.9,"wind_gust":1.1,"dew_point":50.5,"wind_chill":57.7,"heat_index":57.7,"pressure":29.86,"precip_rate":0,"precip_total":0,"humidity":77,"wind_dir":302},{"station":"KCAMALIB62","date":"2022-12-29 15:54:00","temperature":57.7,"wind_speed":0.4,"wind_gust":1.1,"dew_point":50.5,"wind_chill":57.7,"heat_index":57.7,"pressure":29.86,"precip_rate":0,"precip_total":0,"humidity":77,"wind_dir":304},{"station":"KCAMALIB62","date":"2022-12-29 15:59:00","temperature":57.7,"wind_speed":0.7,"wind_gust":1.1,"dew_point":50.2,"wind_chill":57.7,"heat_index":57.7,"pressure":29.86,"precip_rate":0,"precip_total":0,"humidity":76,"wind_dir":338},{"station":"KCAMALIB62","date":"2022-12-29 16:04:00","temperature":57.7,"wind_speed":0,"wind_gust":0,"dew_point":50.2,"wind_chill":57.7,"heat_index":57.7,"pressure":29.86,"precip_rate":0,"precip_total":0,"humidity":76,"wind_dir":304},{"station":"KCAMALIB62","date":"2022-12-29 16:09:00","temperature":57.7,"wind_speed":0,"wind_gust":0,"dew_point":50.2,"wind_chill":57.7,"heat_index":57.7,"pressure":29.86,"precip_rate":0,"precip_total":0,"humidity":76,"wind_dir":304},{"station":"KCAMALIB62","date":"2022-12-29 16:14:00","temperature":57.6,"wind_speed":0,"wind_gust":0,"dew_point":50.1,"wind_chill":57.6,"heat_index":57.6,"pressure":29.87,"precip_rate":0,"precip_total":0,"humidity":76,"wind_dir":301},{"station":"KCAMALIB62","date":"2022-12-29 16:19:00","temperature":57.6,"wind_speed":0,"wind_gust":0,"dew_point":49.7,"wind_chill":57.6,"heat_index":57.6,"pressure":29.86,"precip_rate":0,"precip_total":0,"humidity":75,"wind_dir":304},{"station":"KCAMALIB62","date":"2022-12-29 16:24:00","temperature":57.4,"wind_speed":0,"wind_gust":0,"dew_point":49.5,"wind_chill":57.4,"heat_index":57.4,"pressure":29.86,"precip_rate":0,"precip_total":0,"humidity":75,"wind_dir":298},{"station":"KCAMALIB62","date":"2022-12-29 16:29:00","temperature":57.4,"wind_speed":0,"wind_gust":0,"dew_point":49.2,"wind_chill":57.4,"heat_index":57.4,"pressure":29.86,"precip_rate":0,"precip_total":0,"humidity":74,"wind_dir":301},{"station":"KCAMALIB62","date":"2022-12-29 16:34:00","temperature":57.2,"wind_speed":0,"wind_gust":0,"dew_point":49.3,"wind_chill":57.2,"heat_index":57.2,"pressure":29.86,"precip_rate":0,"precip_total":0,"humidity":75,"wind_dir":297},{"station":"KCAMALIB62","date":"2022-12-29 16:39:00","temperature":57.4,"wind_speed":0.2,"wind_gust":1.1,"dew_point":50.1,"wind_chill":57.4,"heat_index":57.4,"pressure":29.86,"precip_rate":0,"precip_total":0,"humidity":77,"wind_dir":260},{"station":"KCAMALIB62","date":"2022-12-29 16:44:00","temperature":57,"wind_speed":0,"wind_gust":0,"dew_point":49.6,"wind_chill":57,"heat_index":57,"pressure":29.86,"precip_rate":0,"precip_total":0,"humidity":77,"wind_dir":297},{"station":"KCAMALIB62","date":"2022-12-29 16:49:00","temperature":57,"wind_speed":0,"wind_gust":0,"dew_point":50.6,"wind_chill":57,"heat_index":57,"pressure":29.86,"precip_rate":0,"precip_total":0,"humidity":79,"wind_dir":305},{"station":"KCAMALIB62","date":"2022-12-29 16:54:00","temperature":56.8,"wind_speed":0,"wind_gust":0,"dew_point":50.6,"wind_chill":56.8,"heat_index":56.8,"pressure":29.86,"precip_rate":0,"precip_total":0,"humidity":80,"wind_dir":306},{"station":"KCAMALIB62","date":"2022-12-29 16:59:00","temperature":56.5,"wind_speed":0,"wind_gust":0,"dew_point":50.7,"wind_chill":56.5,"heat_index":56.5,"pressure":29.86,"precip_rate":0,"precip_total":0,"humidity":81,"wind_dir":306},{"station":"KCAMALIB62","date":"2022-12-29 17:04:00","temperature":56.3,"wind_speed":0,"wind_gust":0,"dew_point":50.7,"wind_chill":56.3,"heat_index":56.3,"pressure":29.87,"precip_rate":0,"precip_total":0,"humidity":82,"wind_dir":315},{"station":"KCAMALIB62","date":"2022-12-29 17:09:00","temperature":56.1,"wind_speed":0.7,"wind_gust":2.2,"dew_point":50.7,"wind_chill":56.1,"heat_index":56.1,"pressure":29.87,"precip_rate":0,"precip_total":0,"humidity":82,"wind_dir":326},{"station":"KCAMALIB62","date":"2022-12-29 17:14:00","temperature":55.9,"wind_speed":0.9,"wind_gust":1.1,"dew_point":50.5,"wind_chill":55.9,"heat_index":55.9,"pressure":29.87,"precip_rate":0,"precip_total":0,"humidity":82,"wind_dir":326},{"station":"KCAMALIB62","date":"2022-12-29 17:19:00","temperature":55.9,"wind_speed":1.1,"wind_gust":1.1,"dew_point":50.5,"wind_chill":55.9,"heat_index":55.9,"pressure":29.87,"precip_rate":0,"precip_total":0,"humidity":82,"wind_dir":329},{"station":"KCAMALIB62","date":"2022-12-29 17:24:00","temperature":55.9,"wind_speed":1.3,"wind_gust":2.2,"dew_point":50.5,"wind_chill":55.9,"heat_index":55.9,"pressure":29.88,"precip_rate":0,"precip_total":0,"humidity":82,"wind_dir":328},{"station":"KCAMALIB62","date":"2022-12-29 17:29:00","temperature":55.9,"wind_speed":0.2,"wind_gust":1.1,"dew_point":50.5,"wind_chill":55.9,"heat_index":55.9,"pressure":29.88,"precip_rate":0,"precip_total":0,"humidity":82,"wind_dir":322},{"station":"KCAMALIB62","date":"2022-12-29 17:34:00","temperature":55.9,"wind_speed":0.9,"wind_gust":1.1,"dew_point":50.5,"wind_chill":55.9,"heat_index":55.9,"pressure":29.87,"precip_rate":0,"precip_total":0,"humidity":82,"wind_dir":321},{"station":"KCAMALIB62","date":"2022-12-29 17:39:00","temperature":55.9,"wind_speed":0,"wind_gust":0,"dew_point":50.5,"wind_chill":55.9,"heat_index":55.9,"pressure":29.87,"precip_rate":0,"precip_total":0,"humidity":82,"wind_dir":302},{"station":"KCAMALIB62","date":"2022-12-29 17:44:00","temperature":55.9,"wind_speed":0,"wind_gust":0,"dew_point":50.8,"wind_chill":55.9,"heat_index":55.9,"pressure":29.87,"precip_rate":0,"precip_total":0,"humidity":83,"wind_dir":310},{"station":"KCAMALIB62","date":"2022-12-29 17:49:00","temperature":55.9,"wind_speed":0.4,"wind_gust":1.1,"dew_point":50.8,"wind_chill":55.9,"heat_index":55.9,"pressure":29.87,"precip_rate":0,"precip_total":0,"humidity":83,"wind_dir":313},{"station":"KCAMALIB62","date":"2022-12-29 17:54:00","temperature":55.8,"wind_speed":0,"wind_gust":0,"dew_point":50.7,"wind_chill":55.8,"heat_index":55.8,"pressure":29.88,"precip_rate":0,"precip_total":0,"humidity":83,"wind_dir":305},{"station":"KCAMALIB62","date":"2022-12-29 17:59:00","temperature":55.9,"wind_speed":0,"wind_gust":0,"dew_point":50.8,"wind_chill":55.9,"heat_index":55.9,"pressure":29.88,"precip_rate":0,"precip_total":0,"humidity":83,"wind_dir":303},{"station":"KCAMALIB62","date":"2022-12-29 18:04:00","temperature":55.9,"wind_speed":0.7,"wind_gust":1.1,"dew_point":50.8,"wind_chill":55.9,"heat_index":55.9,"pressure":29.88,"precip_rate":0,"precip_total":0,"humidity":83,"wind_dir":323},{"station":"KCAMALIB62","date":"2022-12-29 18:09:00","temperature":55.9,"wind_speed":0,"wind_gust":0,"dew_point":50.5,"wind_chill":55.9,"heat_index":55.9,"pressure":29.89,"precip_rate":0,"precip_total":0,"humidity":82,"wind_dir":311},{"station":"KCAMALIB62","date":"2022-12-29 18:14:00","temperature":55.9,"wind_speed":0,"wind_gust":0,"dew_point":50.5,"wind_chill":55.9,"heat_index":55.9,"pressure":29.89,"precip_rate":0,"precip_total":0,"humidity":82,"wind_dir":303},{"station":"KCAMALIB62","date":"2022-12-29 18:19:00","temperature":55.9,"wind_speed":0,"wind_gust":0,"dew_point":50.8,"wind_chill":55.9,"heat_index":55.9,"pressure":29.89,"precip_rate":0,"precip_total":0,"humidity":83,"wind_dir":311},{"station":"KCAMALIB62","date":"2022-12-29 18:24:00","temperature":55.9,"wind_speed":0,"wind_gust":0,"dew_point":50.5,"wind_chill":55.9,"heat_index":55.9,"pressure":29.89,"precip_rate":0,"precip_total":0,"humidity":82,"wind_dir":304},{"station":"KCAMALIB62","date":"2022-12-29 18:29:00","temperature":55.9,"wind_speed":0,"wind_gust":0,"dew_point":50.8,"wind_chill":55.9,"heat_index":55.9,"pressure":29.89,"precip_rate":0,"precip_total":0,"humidity":83,"wind_dir":305},{"station":"KCAMALIB62","date":"2022-12-29 18:34:00","temperature":55.9,"wind_speed":0,"wind_gust":0,"dew_point":50.8,"wind_chill":55.9,"heat_index":55.9,"pressure":29.89,"precip_rate":0,"precip_total":0,"humidity":83,"wind_dir":303},{"station":"KCAMALIB62","date":"2022-12-29 18:38:00","temperature":55.9,"wind_speed":0,"wind_gust":0,"dew_point":50.8,"wind_chill":55.9,"heat_index":55.9,"pressure":29.89,"precip_rate":0,"precip_total":0,"humidity":83,"wind_dir":302},{"station":"KCAMALIB62","date":"2022-12-29 18:44:00","temperature":55.8,"wind_speed":0,"wind_gust":0,"dew_point":51,"wind_chill":55.8,"heat_index":55.8,"pressure":29.88,"precip_rate":0,"precip_total":0,"humidity":84,"wind_dir":303},{"station":"KCAMALIB62","date":"2022-12-29 18:49:00","temperature":55.6,"wind_speed":0,"wind_gust":0,"dew_point":50.8,"wind_chill":55.6,"heat_index":55.6,"pressure":29.88,"precip_rate":0,"precip_total":0,"humidity":84,"wind_dir":303},{"station":"KCAMALIB62","date":"2022-12-29 18:54:00","temperature":55.6,"wind_speed":0,"wind_gust":0,"dew_point":50.8,"wind_chill":55.6,"heat_index":55.6,"pressure":29.88,"precip_rate":0,"precip_total":0,"humidity":84,"wind_dir":302},{"station":"KCAMALIB62","date":"2022-12-29 18:59:00","temperature":55.4,"wind_speed":0.9,"wind_gust":1.1,"dew_point":51,"wind_chill":55.4,"heat_index":55.4,"pressure":29.9,"precip_rate":0,"precip_total":0,"humidity":85,"wind_dir":296},{"station":"KCAMALIB62","date":"2022-12-29 19:04:00","temperature":55.6,"wind_speed":0.2,"wind_gust":1.1,"dew_point":51.2,"wind_chill":55.6,"heat_index":55.6,"pressure":29.89,"precip_rate":0,"precip_total":0,"humidity":85,"wind_dir":308},{"station":"KCAMALIB62","date":"2022-12-29 19:09:00","temperature":55.4,"wind_speed":0,"wind_gust":0,"dew_point":51,"wind_chill":55.4,"heat_index":55.4,"pressure":29.89,"precip_rate":0,"precip_total":0,"humidity":85,"wind_dir":305},{"station":"KCAMALIB62","date":"2022-12-29 19:14:00","temperature":55.4,"wind_speed":0,"wind_gust":0,"dew_point":51,"wind_chill":55.4,"heat_index":55.4,"pressure":29.89,"precip_rate":0,"precip_total":0,"humidity":85,"wind_dir":301},{"station":"KCAMALIB62","date":"2022-12-29 19:19:00","temperature":55.4,"wind_speed":0.2,"wind_gust":1.1,"dew_point":51,"wind_chill":55.4,"heat_index":55.4,"pressure":29.89,"precip_rate":0,"precip_total":0,"humidity":85,"wind_dir":296},{"station":"KCAMALIB62","date":"2022-12-29 19:24:00","temperature":55.4,"wind_speed":0.2,"wind_gust":1.1,"dew_point":51,"wind_chill":55.4,"heat_index":55.4,"pressure":29.89,"precip_rate":0,"precip_total":0,"humidity":85,"wind_dir":301},{"station":"KCAMALIB62","date":"2022-12-29 19:29:00","temperature":55.4,"wind_speed":0.4,"wind_gust":1.1,"dew_point":51,"wind_chill":55.4,"heat_index":55.4,"pressure":29.9,"precip_rate":0,"precip_total":0,"humidity":85,"wind_dir":307},{"station":"KCAMALIB62","date":"2022-12-29 19:34:00","temperature":55.4,"wind_speed":0,"wind_gust":0,"dew_point":51,"wind_chill":55.4,"heat_index":55.4,"pressure":29.89,"precip_rate":0,"precip_total":0,"humidity":85,"wind_dir":307},{"station":"KCAMALIB62","date":"2022-12-29 19:39:00","temperature":55.4,"wind_speed":0.7,"wind_gust":1.1,"dew_point":50.6,"wind_chill":55.4,"heat_index":55.4,"pressure":29.89,"precip_rate":0,"precip_total":0,"humidity":84,"wind_dir":325},{"station":"KCAMALIB62","date":"2022-12-29 19:44:00","temperature":55.6,"wind_speed":0.2,"wind_gust":1.1,"dew_point":50.8,"wind_chill":55.6,"heat_index":55.6,"pressure":29.9,"precip_rate":0,"precip_total":0,"humidity":84,"wind_dir":313},{"station":"KCAMALIB62","date":"2022-12-29 19:49:00","temperature":55.8,"wind_speed":0.2,"wind_gust":1.1,"dew_point":51,"wind_chill":55.8,"heat_index":55.8,"pressure":29.9,"precip_rate":0,"precip_total":0,"humidity":84,"wind_dir":298},{"station":"KCAMALIB62","date":"2022-12-29 19:54:00","temperature":55.8,"wind_speed":0,"wind_gust":0,"dew_point":51,"wind_chill":55.8,"heat_index":55.8,"pressure":29.9,"precip_rate":0,"precip_total":0,"humidity":84,"wind_dir":304},{"station":"KCAMALIB62","date":"2022-12-29 19:59:00","temperature":55.6,"wind_speed":0,"wind_gust":0,"dew_point":51.2,"wind_chill":55.6,"heat_index":55.6,"pressure":29.91,"precip_rate":0,"precip_total":0,"humidity":85,"wind_dir":303},{"station":"KCAMALIB62","date":"2022-12-29 20:04:00","temperature":55.6,"wind_speed":0,"wind_gust":0,"dew_point":51.2,"wind_chill":55.6,"heat_index":55.6,"pressure":29.91,"precip_rate":0,"precip_total":0,"humidity":85,"wind_dir":300},{"station":"KCAMALIB62","date":"2022-12-29 20:09:00","temperature":55.6,"wind_speed":0,"wind_gust":0,"dew_point":51.2,"wind_chill":55.6,"heat_index":55.6,"pressure":29.91,"precip_rate":0,"precip_total":0,"humidity":85,"wind_dir":303},{"station":"KCAMALIB62","date":"2022-12-29 20:14:00","temperature":55.6,"wind_speed":0,"wind_gust":0,"dew_point":51.2,"wind_chill":55.6,"heat_index":55.6,"pressure":29.91,"precip_rate":0,"precip_total":0,"humidity":85,"wind_dir":306},{"station":"KCAMALIB62","date":"2022-12-29 20:19:00","temperature":55.6,"wind_speed":0,"wind_gust":0,"dew_point":50.8,"wind_chill":55.6,"heat_index":55.6,"pressure":29.91,"precip_rate":0,"precip_total":0,"humidity":84,"wind_dir":302},{"station":"KCAMALIB62","date":"2022-12-29 20:24:00","temperature":55.8,"wind_speed":0,"wind_gust":0,"dew_point":51,"wind_chill":55.8,"heat_index":55.8,"pressure":29.92,"precip_rate":0,"precip_total":0,"humidity":84,"wind_dir":303},{"station":"KCAMALIB62","date":"2022-12-29 20:29:00","temperature":55.8,"wind_speed":0,"wind_gust":0,"dew_point":51,"wind_chill":55.8,"heat_index":55.8,"pressure":29.92,"precip_rate":0,"precip_total":0,"humidity":84,"wind_dir":308},{"station":"KCAMALIB62","date":"2022-12-29 20:34:00","temperature":55.8,"wind_speed":0,"wind_gust":0,"dew_point":51.4,"wind_chill":55.8,"heat_index":55.8,"pressure":29.91,"precip_rate":0,"precip_total":0,"humidity":85,"wind_dir":303},{"station":"KCAMALIB62","date":"2022-12-29 20:39:00","temperature":55.8,"wind_speed":0,"wind_gust":0,"dew_point":51.4,"wind_chill":55.8,"heat_index":55.8,"pressure":29.91,"precip_rate":0,"precip_total":0,"humidity":85,"wind_dir":308},{"station":"KCAMALIB62","date":"2022-12-29 20:44:00","temperature":55.6,"wind_speed":0,"wind_gust":0,"dew_point":51.2,"wind_chill":55.6,"heat_index":55.6,"pressure":29.91,"precip_rate":0,"precip_total":0,"humidity":85,"wind_dir":306},{"station":"KCAMALIB62","date":"2022-12-29 20:49:00","temperature":55.6,"wind_speed":0,"wind_gust":0,"dew_point":51.2,"wind_chill":55.6,"heat_index":55.6,"pressure":29.91,"precip_rate":0,"precip_total":0,"humidity":85,"wind_dir":307},{"station":"KCAMALIB62","date":"2022-12-29 20:53:00","temperature":55.4,"wind_speed":0,"wind_gust":0,"dew_point":51,"wind_chill":55.4,"heat_index":55.4,"pressure":29.91,"precip_rate":0,"precip_total":0,"humidity":85,"wind_dir":303},{"station":"KCAMALIB62","date":"2022-12-29 20:59:00","temperature":55.4,"wind_speed":0,"wind_gust":0,"dew_point":50.6,"wind_chill":55.4,"heat_index":55.4,"pressure":29.91,"precip_rate":0,"precip_total":0,"humidity":84,"wind_dir":307},{"station":"KCAMALIB62","date":"2022-12-29 21:04:00","temperature":55.6,"wind_speed":0,"wind_gust":0,"dew_point":50.8,"wind_chill":55.6,"heat_index":55.6,"pressure":29.91,"precip_rate":0,"precip_total":0,"humidity":84,"wind_dir":309},{"station":"KCAMALIB62","date":"2022-12-29 21:09:00","temperature":55.6,"wind_speed":0.2,"wind_gust":1.1,"dew_point":50.8,"wind_chill":55.6,"heat_index":55.6,"pressure":29.92,"precip_rate":0,"precip_total":0,"humidity":84,"wind_dir":322},{"station":"KCAMALIB62","date":"2022-12-29 21:14:00","temperature":55.6,"wind_speed":0,"wind_gust":0,"dew_point":50.8,"wind_chill":55.6,"heat_index":55.6,"pressure":29.92,"precip_rate":0,"precip_total":0,"humidity":84,"wind_dir":302},{"station":"KCAMALIB62","date":"2022-12-29 21:19:00","temperature":55.4,"wind_speed":0,"wind_gust":0,"dew_point":51,"wind_chill":55.4,"heat_index":55.4,"pressure":29.92,"precip_rate":0,"precip_total":0,"humidity":85,"wind_dir":303},{"station":"KCAMALIB62","date":"2022-12-29 21:24:00","temperature":55.6,"wind_speed":0,"wind_gust":0,"dew_point":51.2,"wind_chill":55.6,"heat_index":55.6,"pressure":29.92,"precip_rate":0,"precip_total":0,"humidity":85,"wind_dir":303},{"station":"KCAMALIB62","date":"2022-12-29 21:29:00","temperature":55.4,"wind_speed":0,"wind_gust":0,"dew_point":51,"wind_chill":55.4,"heat_index":55.4,"pressure":29.93,"precip_rate":0,"precip_total":0,"humidity":85,"wind_dir":307},{"station":"KCAMALIB62","date":"2022-12-29 21:34:00","temperature":55.4,"wind_speed":0.7,"wind_gust":1.1,"dew_point":51,"wind_chill":55.4,"heat_index":55.4,"pressure":29.93,"precip_rate":0,"precip_total":0,"humidity":85,"wind_dir":359},{"station":"KCAMALIB62","date":"2022-12-29 21:39:00","temperature":55.4,"wind_speed":0,"wind_gust":0,"dew_point":50.4,"wind_chill":55.4,"heat_index":55.4,"pressure":29.92,"precip_rate":0,"precip_total":0,"humidity":84,"wind_dir":306},{"station":"KCAMALIB62","date":"2022-12-29 21:44:00","temperature":55.6,"wind_speed":0.4,"wind_gust":1.1,"dew_point":50.5,"wind_chill":55.6,"heat_index":55.6,"pressure":29.93,"precip_rate":0,"precip_total":0,"humidity":83,"wind_dir":341},{"station":"KCAMALIB62","date":"2022-12-29 21:49:00","temperature":55.8,"wind_speed":0,"wind_gust":0,"dew_point":50.7,"wind_chill":55.8,"heat_index":55.8,"pressure":29.93,"precip_rate":0,"precip_total":0,"humidity":83,"wind_dir":311},{"station":"KCAMALIB62","date":"2022-12-29 21:54:00","temperature":55.8,"wind_speed":0.9,"wind_gust":1.1,"dew_point":50.7,"wind_chill":55.8,"heat_index":55.8,"pressure":29.93,"precip_rate":0,"precip_total":0,"humidity":83,"wind_dir":316},{"station":"KCAMALIB62","date":"2022-12-29 21:59:00","temperature":55.8,"wind_speed":0,"wind_gust":0,"dew_point":50.7,"wind_chill":55.8,"heat_index":55.8,"pressure":29.93,"precip_rate":0,"precip_total":0,"humidity":83,"wind_dir":307},{"station":"KCAMALIB62","date":"2022-12-29 22:04:00","temperature":55.8,"wind_speed":0,"wind_gust":0,"dew_point":50.7,"wind_chill":55.8,"heat_index":55.8,"pressure":29.94,"precip_rate":0,"precip_total":0,"humidity":83,"wind_dir":303},{"station":"KCAMALIB62","date":"2022-12-29 22:09:00","temperature":55.8,"wind_speed":0,"wind_gust":0,"dew_point":50.7,"wind_chill":55.8,"heat_index":55.8,"pressure":29.94,"precip_rate":0,"precip_total":0,"humidity":83,"wind_dir":306},{"station":"KCAMALIB62","date":"2022-12-29 22:14:00","temperature":55.6,"wind_speed":0,"wind_gust":0,"dew_point":50.8,"wind_chill":55.6,"heat_index":55.6,"pressure":29.93,"precip_rate":0,"precip_total":0,"humidity":84,"wind_dir":307},{"station":"KCAMALIB62","date":"2022-12-29 22:19:00","temperature":55.6,"wind_speed":0,"wind_gust":0,"dew_point":50.8,"wind_chill":55.6,"heat_index":55.6,"pressure":29.94,"precip_rate":0,"precip_total":0,"humidity":84,"wind_dir":308},{"station":"KCAMALIB62","date":"2022-12-29 22:24:00","temperature":55.4,"wind_speed":0,"wind_gust":0,"dew_point":50.6,"wind_chill":55.4,"heat_index":55.4,"pressure":29.94,"precip_rate":0,"precip_total":0,"humidity":84,"wind_dir":299},{"station":"KCAMALIB62","date":"2022-12-29 22:29:00","temperature":55.4,"wind_speed":0,"wind_gust":0,"dew_point":51,"wind_chill":55.4,"heat_index":55.4,"pressure":29.94,"precip_rate":0,"precip_total":0,"humidity":85,"wind_dir":305},{"station":"KCAMALIB62","date":"2022-12-29 22:33:00","temperature":55.2,"wind_speed":0,"wind_gust":0,"dew_point":50.8,"wind_chill":55.2,"heat_index":55.2,"pressure":29.94,"precip_rate":0,"precip_total":0,"humidity":85,"wind_dir":303},{"station":"KCAMALIB62","date":"2022-12-29 22:39:00","temperature":55,"wind_speed":0,"wind_gust":0,"dew_point":50.6,"wind_chill":55,"heat_index":55,"pressure":29.93,"precip_rate":0,"precip_total":0,"humidity":85,"wind_dir":323},{"station":"KCAMALIB62","date":"2022-12-29 22:44:00","temperature":55,"wind_speed":0,"wind_gust":0,"dew_point":50.6,"wind_chill":55,"heat_index":55,"pressure":29.93,"precip_rate":0,"precip_total":0,"humidity":85,"wind_dir":307},{"station":"KCAMALIB62","date":"2022-12-29 22:49:00","temperature":54.9,"wind_speed":0,"wind_gust":0,"dew_point":50.6,"wind_chill":54.9,"heat_index":54.9,"pressure":29.93,"precip_rate":0,"precip_total":0,"humidity":86,"wind_dir":302},{"station":"KCAMALIB62","date":"2022-12-29 22:54:00","temperature":54.5,"wind_speed":0,"wind_gust":0,"dew_point":50.4,"wind_chill":54.5,"heat_index":54.5,"pressure":29.94,"precip_rate":0,"precip_total":0,"humidity":86,"wind_dir":304},{"station":"KCAMALIB62","date":"2022-12-29 22:59:00","temperature":54.3,"wind_speed":0,"wind_gust":0,"dew_point":50.5,"wind_chill":54.3,"heat_index":54.3,"pressure":29.94,"precip_rate":0,"precip_total":0,"humidity":87,"wind_dir":301},{"station":"KCAMALIB62","date":"2022-12-29 23:04:00","temperature":54.3,"wind_speed":0,"wind_gust":0,"dew_point":50.5,"wind_chill":54.3,"heat_index":54.3,"pressure":29.94,"precip_rate":0,"precip_total":0,"humidity":87,"wind_dir":303},{"station":"KCAMALIB62","date":"2022-12-29 23:09:00","temperature":54.5,"wind_speed":0,"wind_gust":0,"dew_point":50.7,"wind_chill":54.5,"heat_index":54.5,"pressure":29.94,"precip_rate":0,"precip_total":0,"humidity":87,"wind_dir":304},{"station":"KCAMALIB62","date":"2022-12-29 23:13:00","temperature":54.5,"wind_speed":0,"wind_gust":0,"dew_point":51,"wind_chill":54.5,"heat_index":54.5,"pressure":29.94,"precip_rate":0,"precip_total":0,"humidity":88,"wind_dir":304},{"station":"KCAMALIB62","date":"2022-12-29 23:19:00","temperature":54.5,"wind_speed":0,"wind_gust":0,"dew_point":51,"wind_chill":54.5,"heat_index":54.5,"pressure":29.95,"precip_rate":0,"precip_total":0,"humidity":88,"wind_dir":312},{"station":"KCAMALIB62","date":"2022-12-29 23:24:00","temperature":54.7,"wind_speed":0,"wind_gust":0,"dew_point":51,"wind_chill":54.7,"heat_index":54.7,"pressure":29.94,"precip_rate":0,"precip_total":0,"humidity":88,"wind_dir":306},{"station":"KCAMALIB62","date":"2022-12-29 23:29:00","temperature":54.7,"wind_speed":0,"wind_gust":0,"dew_point":50.9,"wind_chill":54.7,"heat_index":54.7,"pressure":29.95,"precip_rate":0,"precip_total":0,"humidity":87,"wind_dir":305},{"station":"KCAMALIB62","date":"2022-12-29 23:34:00","temperature":54.7,"wind_speed":0,"wind_gust":0,"dew_point":50.9,"wind_chill":54.7,"heat_index":54.7,"pressure":29.94,"precip_rate":0,"precip_total":0,"humidity":87,"wind_dir":304},{"station":"KCAMALIB62","date":"2022-12-29 23:39:00","temperature":54.7,"wind_speed":0,"wind_gust":0,"dew_point":50.9,"wind_chill":54.7,"heat_index":54.7,"pressure":29.94,"precip_rate":0,"precip_total":0,"humidity":87,"wind_dir":305},{"station":"KCAMALIB62","date":"2022-12-29 23:44:00","temperature":54.9,"wind_speed":0,"wind_gust":0,"dew_point":51.1,"wind_chill":54.9,"heat_index":54.9,"pressure":29.94,"precip_rate":0,"precip_total":0,"humidity":87,"wind_dir":304},{"station":"KCAMALIB62","date":"2022-12-29 23:49:00","temperature":54.9,"wind_speed":0,"wind_gust":0,"dew_point":51.1,"wind_chill":54.9,"heat_index":54.9,"pressure":29.94,"precip_rate":0,"precip_total":0,"humidity":87,"wind_dir":303},{"station":"KCAMALIB62","date":"2022-12-29 23:54:00","temperature":54.9,"wind_speed":0,"wind_gust":0,"dew_point":51.1,"wind_chill":54.9,"heat_index":54.9,"pressure":29.94,"precip_rate":0,"precip_total":0,"humidity":87,"wind_dir":304},{"station":"KCAMALIB62","date":"2022-12-29 23:59:00","temperature":55,"wind_speed":0,"wind_gust":0,"dew_point":51.2,"wind_chill":55,"heat_index":55,"pressure":29.94,"precip_rate":0,"precip_total":0,"humidity":87,"wind_dir":305}]